[{"Label":"AAK.ST","Name":"AAK AB","Change":"-0.52%","Volume":13684,"Open":580.00,"DaysLow":573.00,"DaysHigh":581.50,"LastTradePriceOnly":577.00,"LastTradeTime":"10:18am","LastTradeDate":"2/13/2017","Cap":"LargeCap"},{"Label":"ABB.ST","Name":"ABB Ltd","Change":"+0.15%","Volume":132375,"Open":203.90,"DaysLow":203.60,"DaysHigh":204.40,"LastTradePriceOnly":204.10,"LastTradeTime":"10:16am","LastTradeDate":"2/13/2017","Cap":"LargeCap"},{"Label":"AHSL.ST","Name":"Ahlsell AB","Change":"-0.26%","Volume":16491,"Open":57.60,"DaysLow":57.05,"DaysHigh":57.60,"LastTradePriceOnly":57.20,"LastTradeTime":"10:17am","LastTradeDate":"2/13/2017","Cap":"LargeCap"},{"Label":"ALFA.ST","Name":"Alfa Laval AB","Change":"+0.18%","Volume":77657,"Open":165.80,"DaysLow":165.50,"DaysHigh":166.40,"LastTradePriceOnly":166.10,"LastTradeTime":"10:17am","LastTradeDate":"2/13/2017","Cap":"LargeCap"},{"Label":"ASSA-B.ST","Name":"ASSA ABLOY AB ser. B","Change":"+1.35%","Volume":453223,"Open":174.00,"DaysLow":173.10,"DaysHigh":175.00,"LastTradePriceOnly":173.30,"LastTradeTime":"10:18am","LastTradeDate":"2/13/2017","Cap":"LargeCap"},{"Label":"AZN.ST","Name":"AstraZeneca PLC","Change":"+0.86%","Volume":112674,"Open":521.00,"DaysLow":521.00,"DaysHigh":526.00,"LastTradePriceOnly":525.50,"LastTradeTime":"10:17am","LastTradeDate":"2/13/2017","Cap":"LargeCap"},{"Label":"ATCO-A.ST","Name":"Atlas Copco AB ser. A","Change":"+0.62%","Volume":226620,"Open":289.60,"DaysLow":289.20,"DaysHigh":290.70,"LastTradePriceOnly":290.10,"LastTradeTime":"10:17am","LastTradeDate":"2/13/2017","Cap":"LargeCap"},{"Label":"ATCO-B.ST","Name":"Atlas Copco AB ser. B","Change":"+0.46%","Volume":100845,"Open":262.00,"DaysLow":261.80,"DaysHigh":263.30,"LastTradePriceOnly":262.40,"LastTradeTime":"10:17am","LastTradeDate":"2/13/2017","Cap":"LargeCap"},{"Label":"ATRLJ-B.ST","Name":"Atrium Ljungberg AB ser. B","Change":"+1.18%","Volume":10689,"Open":145.50,"DaysLow":145.50,"DaysHigh":146.30,"LastTradePriceOnly":145.80,"LastTradeTime":"10:16am","LastTradeDate":"2/13/2017","Cap":"LargeCap"},{"Label":"ALIV-SDB.ST","Name":"Autoliv Inc. SDB","Change":"+0.85%","Volume":44647,"Open":947.00,"DaysLow":941.50,"DaysHigh":947.00,"LastTradePriceOnly":946.00,"LastTradeTime":"10:17am","LastTradeDate":"2/13/2017","Cap":"LargeCap"},{"Label":"AXFO.ST","Name":"Axfood AB","Change":"-0.44%","Volume":123201,"Open":135.00,"DaysLow":134.10,"DaysHigh":135.60,"LastTradePriceOnly":134.40,"LastTradeTime":"10:16am","LastTradeDate":"2/13/2017","Cap":"LargeCap"},{"Label":"AXIS.ST","Name":"Axis AB","Change":"+0.48%","Volume":258,"Open":354.00,"DaysLow":354.00,"DaysHigh":360.10,"LastTradePriceOnly":355.00,"LastTradeTime":"10:04am","LastTradeDate":"2/13/2017","Cap":"LargeCap"},{"Label":"BETS-B.ST","Name":"Betsson AB ser. B","Change":"-1.55%","Volume":297107,"Open":84.45,"DaysLow":82.45,"DaysHigh":84.60,"LastTradePriceOnly":82.80,"LastTradeTime":"10:17am","LastTradeDate":"2/13/2017","Cap":"LargeCap"},{"Label":"BILL.ST","Name":"BillerudKorsns AB","Change":"+0.27%","Volume":56094,"Open":150.80,"DaysLow":149.90,"DaysHigh":151.20,"LastTradePriceOnly":150.50,"LastTradeTime":"10:18am","LastTradeDate":"2/13/2017","Cap":"LargeCap"},{"Label":"BOL.ST","Name":"Boliden AB","Change":"+2.49%","Volume":1097900,"Open":282.60,"DaysLow":282.50,"DaysHigh":290.50,"LastTradePriceOnly":284.30,"LastTradeTime":"10:18am","LastTradeDate":"2/13/2017","Cap":"LargeCap"},{"Label":"BONAV-A.ST","Name":"Bonava AB ser. A","Change":"-0.07%","Volume":79,"Open":140.30,"DaysLow":139.00,"DaysHigh":140.40,"LastTradePriceOnly":139.00,"LastTradeTime":"10:07am","LastTradeDate":"2/13/2017","Cap":"LargeCap"},{"Label":"BONAV-B.ST","Name":"Bonava AB ser. B","Change":"-0.50%","Volume":7619,"Open":140.20,"DaysLow":139.50,"DaysHigh":140.20,"LastTradePriceOnly":139.50,"LastTradeTime":"10:15am","LastTradeDate":"2/13/2017","Cap":"LargeCap"},{"Label":"CAST.ST","Name":"Castellum AB","Change":"+0.00%","Volume":77927,"Open":124.00,"DaysLow":123.00,"DaysHigh":124.20,"LastTradePriceOnly":123.30,"LastTradeTime":"10:17am","LastTradeDate":"2/13/2017","Cap":"LargeCap"},{"Label":"COMH.ST","Name":"Com Hem Holding AB","Change":"-0.05%","Volume":16577,"Open":91.40,"DaysLow":91.05,"DaysHigh":91.40,"LastTradePriceOnly":91.25,"LastTradeTime":"10:17am","LastTradeDate":"2/13/2017","Cap":"LargeCap"},{"Label":"DOM.ST","Name":"Dometic Group AB","Change":"-0.57%","Volume":71500,"Open":70.55,"DaysLow":69.90,"DaysHigh":70.75,"LastTradePriceOnly":70.10,"LastTradeTime":"10:17am","LastTradeDate":"2/13/2017","Cap":"LargeCap"},{"Label":"ELUX-A.ST","Name":"Electrolux, AB ser. A","Change":"+1.06%","Volume":70,"Open":237.40,"DaysLow":237.40,"DaysHigh":238.60,"LastTradePriceOnly":238.50,"LastTradeTime":"10:14am","LastTradeDate":"2/13/2017","Cap":"LargeCap"},{"Label":"ELUX-B.ST","Name":"Electrolux, AB ser. B","Change":"+0.04%","Volume":127267,"Open":230.60,"DaysLow":228.90,"DaysHigh":230.60,"LastTradePriceOnly":229.50,"LastTradeTime":"10:16am","LastTradeDate":"2/13/2017","Cap":"LargeCap"},{"Label":"EKTA-B.ST","Name":"Elekta AB ser. B","Change":"+0.24%","Volume":105067,"Open":81.80,"DaysLow":81.15,"DaysHigh":81.90,"LastTradePriceOnly":81.90,"LastTradeTime":"10:18am","LastTradeDate":"2/13/2017","Cap":"LargeCap"},{"Label":"ERIC-A.ST","Name":"Ericsson, Telefonab. L M ser. A","Change":"+0.00%","Volume":5856,"Open":51.25,"DaysLow":51.15,"DaysHigh":51.60,"LastTradePriceOnly":51.15,"LastTradeTime":"9:54am","LastTradeDate":"2/13/2017","Cap":"LargeCap"},{"Label":"ERIC-B.ST","Name":"Ericsson, Telefonab. L M ser. B","Change":"+0.00%","Volume":1040064,"Open":50.95,"DaysLow":50.65,"DaysHigh":51.00,"LastTradePriceOnly":50.85,"LastTradeTime":"10:16am","LastTradeDate":"2/13/2017","Cap":"LargeCap"},{"Label":"FABG.ST","Name":"Fabege AB","Change":"-0.39%","Volume":59184,"Open":153.20,"DaysLow":151.80,"DaysHigh":153.60,"LastTradePriceOnly":152.30,"LastTradeTime":"10:18am","LastTradeDate":"2/13/2017","Cap":"LargeCap"},{"Label":"BALD-B.ST","Name":"Fastighets AB Balder ser. B","Change":"-0.10%","Volume":56746,"Open":195.00,"DaysLow":192.50,"DaysHigh":196.10,"LastTradePriceOnly":194.30,"LastTradeTime":"10:16am","LastTradeDate":"2/13/2017","Cap":"LargeCap"},{"Label":"BALD-PREF.ST","Name":"Fastighets AB Balder pref","Change":"+0.47%","Volume":645,"Open":323.00,"DaysLow":322.80,"DaysHigh":325.00,"LastTradePriceOnly":324.00,"LastTradeTime":"10:18am","LastTradeDate":"2/13/2017","Cap":"LargeCap"},{"Label":"FING-B.ST","Name":"Fingerprint Cards AB ser. B","Change":"+2.06%","Volume":2906406,"Open":56.40,"DaysLow":54.60,"DaysHigh":57.10,"LastTradePriceOnly":57.10,"LastTradeTime":"10:18am","LastTradeDate":"2/13/2017","Cap":"LargeCap"},{"Label":"GETI-B.ST","Name":"Getinge AB ser. B","Change":"-0.07%","Volume":95156,"Open":146.60,"DaysLow":145.50,"DaysHigh":147.30,"LastTradePriceOnly":146.30,"LastTradeTime":"10:18am","LastTradeDate":"2/13/2017","Cap":"LargeCap"},{"Label":"SHB-A.ST","Name":"Svenska Handelsbanken ser. A","Change":"+0.00%","Volume":265877,"Open":130.80,"DaysLow":130.20,"DaysHigh":131.20,"LastTradePriceOnly":130.50,"LastTradeTime":"10:16am","LastTradeDate":"2/13/2017","Cap":"LargeCap"},{"Label":"SHB-B.ST","Name":"Svenska Handelsbanken ser. B","Change":"-0.53%","Volume":11163,"Open":131.40,"DaysLow":130.40,"DaysHigh":131.90,"LastTradePriceOnly":130.50,"LastTradeTime":"10:16am","LastTradeDate":"2/13/2017","Cap":"LargeCap"},{"Label":"HM-B.ST","Name":"Hennes & Mauritz AB, H & M ser.","Change":"-0.28%","Volume":449549,"Open":247.50,"DaysLow":246.00,"DaysHigh":248.00,"LastTradePriceOnly":246.30,"LastTradeTime":"10:17am","LastTradeDate":"2/13/2017","Cap":"LargeCap"},{"Label":"HEXA-B.ST","Name":"Hexagon AB ser. B","Change":"-0.08%","Volume":24789,"Open":367.00,"DaysLow":365.30,"DaysHigh":368.00,"LastTradePriceOnly":366.70,"LastTradeTime":"10:15am","LastTradeDate":"2/13/2017","Cap":"LargeCap"},{"Label":"HPOL-B.ST","Name":"HEXPOL AB ser. B","Change":"-0.28%","Volume":39339,"Open":89.00,"DaysLow":88.95,"DaysHigh":89.55,"LastTradePriceOnly":89.05,"LastTradeTime":"10:17am","LastTradeDate":"2/13/2017","Cap":"LargeCap"},{"Label":"HOLM-A.ST","Name":"Holmen AB ser. A","Change":"+0.00%","Volume":35,"Open":348.50,"DaysLow":335.30,"DaysHigh":348.50,"LastTradePriceOnly":348.30,"LastTradeTime":"9:18am","LastTradeDate":"2/13/2017","Cap":"LargeCap"},{"Label":"HOLM-B.ST","Name":"Holmen AB ser. B","Change":"-0.06%","Volume":11775,"Open":340.80,"DaysLow":340.20,"DaysHigh":343.00,"LastTradePriceOnly":340.50,"LastTradeTime":"10:17am","LastTradeDate":"2/13/2017","Cap":"LargeCap"},{"Label":"HUFV-A.ST","Name":"Hufvudstaden AB ser. A","Change":"-0.76%","Volume":20038,"Open":144.40,"DaysLow":143.40,"DaysHigh":145.00,"LastTradePriceOnly":143.40,"LastTradeTime":"10:15am","LastTradeDate":"2/13/2017","Cap":"LargeCap"},{"Label":"HUFV-C.ST","Name":"Hufvudstaden AB ser. C","Change":"+0.00%","Volume":0,"Open":207.40,"DaysLow":207.40,"DaysHigh":207.40,"LastTradePriceOnly":207.40,"LastTradeTime":"3:01pm","LastTradeDate":"1/24/2017","Cap":"LargeCap"},{"Label":"HUSQ-A.ST","Name":"Husqvarna AB ser. A","Change":"+0.34%","Volume":11295,"Open":72.75,"DaysLow":72.35,"DaysHigh":73.15,"LastTradePriceOnly":72.80,"LastTradeTime":"10:08am","LastTradeDate":"2/13/2017","Cap":"LargeCap"},{"Label":"HUSQ-B.ST","Name":"Husqvarna AB ser. B","Change":"+0.41%","Volume":283359,"Open":72.85,"DaysLow":72.50,"DaysHigh":73.20,"LastTradePriceOnly":73.10,"LastTradeTime":"10:17am","LastTradeDate":"2/13/2017","Cap":"LargeCap"},{"Label":"ICA.ST","Name":"ICA Gruppen AB","Change":"+0.07%","Volume":60180,"Open":287.60,"DaysLow":287.40,"DaysHigh":289.20,"LastTradePriceOnly":287.50,"LastTradeTime":"10:18am","LastTradeDate":"2/13/2017","Cap":"LargeCap"},{"Label":"INDU-A.ST","Name":"Industrivrden, AB ser. A","Change":"-0.21%","Volume":29887,"Open":189.00,"DaysLow":187.50,"DaysHigh":189.00,"LastTradePriceOnly":187.60,"LastTradeTime":"10:13am","LastTradeDate":"2/13/2017","Cap":"LargeCap"},{"Label":"INDU-C.ST","Name":"Industrivrden, AB ser. C","Change":"+0.46%","Volume":42424,"Open":176.70,"DaysLow":175.90,"DaysHigh":176.70,"LastTradePriceOnly":176.40,"LastTradeTime":"10:17am","LastTradeDate":"2/13/2017","Cap":"LargeCap"},{"Label":"INDT.ST","Name":"Indutrade AB","Change":"+0.51%","Volume":18173,"Open":177.00,"DaysLow":176.80,"DaysHigh":178.40,"LastTradePriceOnly":177.90,"LastTradeTime":"10:17am","LastTradeDate":"2/13/2017","Cap":"LargeCap"},{"Label":"IJ.ST","Name":"Intrum Justitia AB","Change":"-0.03%","Volume":23812,"Open":307.00,"DaysLow":304.00,"DaysHigh":307.00,"LastTradePriceOnly":305.70,"LastTradeTime":"10:17am","LastTradeDate":"2/13/2017","Cap":"LargeCap"},{"Label":"INVE-A.ST","Name":"Investor AB ser. A","Change":"+0.11%","Volume":15426,"Open":350.00,"DaysLow":349.30,"DaysHigh":351.20,"LastTradePriceOnly":350.00,"LastTradeTime":"10:17am","LastTradeDate":"2/13/2017","Cap":"LargeCap"},{"Label":"INVE-B.ST","Name":"Investor AB ser. B","Change":"+0.06%","Volume":129516,"Open":356.60,"DaysLow":355.00,"DaysHigh":357.00,"LastTradePriceOnly":355.70,"LastTradeTime":"10:17am","LastTradeDate":"2/13/2017","Cap":"LargeCap"},{"Label":"JM.ST","Name":"JM AB","Change":"+0.39%","Volume":32800,"Open":283.40,"DaysLow":282.90,"DaysHigh":284.60,"LastTradePriceOnly":283.50,"LastTradeTime":"10:17am","LastTradeDate":"2/13/2017","Cap":"LargeCap"},{"Label":"KINV-A.ST","Name":"Kinnevik AB ser. A","Change":"+1.71%","Volume":1867,"Open":240.30,"DaysLow":240.30,"DaysHigh":244.50,"LastTradePriceOnly":244.40,"LastTradeTime":"10:17am","LastTradeDate":"2/13/2017","Cap":"LargeCap"},{"Label":"KINV-B.ST","Name":"Kinnevik AB ser. B","Change":"+0.82%","Volume":119914,"Open":232.70,"DaysLow":232.30,"DaysHigh":233.60,"LastTradePriceOnly":233.40,"LastTradeTime":"10:18am","LastTradeDate":"2/13/2017","Cap":"LargeCap"},{"Label":"KLOV-A.ST","Name":"Klvern AB Ser. A","Change":"+1.559%","Volume":8972,"Open":9.300,"DaysLow":9.200,"DaysHigh":9.445,"LastTradePriceOnly":9.445,"LastTradeTime":"10:12am","LastTradeDate":"2/13/2017","Cap":"LargeCap"},{"Label":"KLOV-B.ST","Name":"Klvern AB Ser. B","Change":"+0.375%","Volume":164478,"Open":9.355,"DaysLow":9.350,"DaysHigh":9.415,"LastTradePriceOnly":9.375,"LastTradeTime":"10:17am","LastTradeDate":"2/13/2017","Cap":"LargeCap"},{"Label":"KLOV-PREF.ST","Name":"Klvern AB pref","Change":"-0.52%","Volume":6122,"Open":288.00,"DaysLow":286.50,"DaysHigh":289.70,"LastTradePriceOnly":286.50,"LastTradeTime":"10:16am","LastTradeDate":"2/13/2017","Cap":"LargeCap"},{"Label":"LATO-B.ST","Name":"Latour, Investmentab. ser. B","Change":"+0.15%","Volume":3467,"Open":343.00,"DaysLow":341.50,"DaysHigh":343.00,"LastTradePriceOnly":341.50,"LastTradeTime":"10:14am","LastTradeDate":"2/13/2017","Cap":"LargeCap"},{"Label":"LIFCO-B.ST","Name":"Lifco AB ser.B","Change":"-0.12%","Volume":3881,"Open":240.00,"DaysLow":240.00,"DaysHigh":244.10,"LastTradePriceOnly":242.00,"LastTradeTime":"10:17am","LastTradeDate":"2/13/2017","Cap":"LargeCap"},{"Label":"LOOM-B.ST","Name":"Loomis AB ser. B","Change":"+0.18%","Volume":12860,"Open":275.00,"DaysLow":274.10,"DaysHigh":276.00,"LastTradePriceOnly":275.50,"LastTradeTime":"10:18am","LastTradeDate":"2/13/2017","Cap":"LargeCap"},{"Label":"LUND-B.ST","Name":"Lundbergfretagen AB, L E ser. B","Change":"+0.00%","Volume":21576,"Open":576.00,"DaysLow":573.00,"DaysHigh":576.50,"LastTradePriceOnly":574.00,"LastTradeTime":"10:18am","LastTradeDate":"2/13/2017","Cap":"LargeCap"},{"Label":"LUMI-SDB.ST","Name":"Lundin Mining Corporation SDB","Change":"+2.84%","Volume":348498,"Open":58.35,"DaysLow":58.35,"DaysHigh":59.80,"LastTradePriceOnly":59.65,"LastTradeTime":"10:18am","LastTradeDate":"2/13/2017","Cap":"LargeCap"},{"Label":"LUPE.ST","Name":"Lundin Petroleum AB","Change":"+1.96%","Volume":370675,"Open":202.10,"DaysLow":201.40,"DaysHigh":205.70,"LastTradePriceOnly":202.50,"LastTradeTime":"10:18am","LastTradeDate":"2/13/2017","Cap":"LargeCap"},{"Label":"MELK.ST","Name":"Melker Schrling AB","Change":"+0.45%","Volume":3550,"Open":553.00,"DaysLow":553.00,"DaysHigh":558.00,"LastTradePriceOnly":556.50,"LastTradeTime":"10:17am","LastTradeDate":"2/13/2017","Cap":"LargeCap"},{"Label":"MIC-SDB.ST","Name":"Millicom International Cellular","Change":"+0.32%","Volume":14246,"Open":476.00,"DaysLow":474.20,"DaysHigh":477.90,"LastTradePriceOnly":475.50,"LastTradeTime":"10:18am","LastTradeDate":"2/13/2017","Cap":"LargeCap"},{"Label":"MTG-A.ST","Name":"Modern Times Group MTG AB ser. ","Change":"+0.00%","Volume":21,"Open":304.70,"DaysLow":299.40,"DaysHigh":304.70,"LastTradePriceOnly":299.40,"LastTradeTime":"9:00am","LastTradeDate":"2/13/2017","Cap":"LargeCap"},{"Label":"MTG-B.ST","Name":"Modern Times Group MTG AB ser. ","Change":"-0.24%","Volume":14483,"Open":287.80,"DaysLow":286.60,"DaysHigh":289.30,"LastTradePriceOnly":287.10,"LastTradeTime":"10:17am","LastTradeDate":"2/13/2017","Cap":"LargeCap"},{"Label":"NCC-A.ST","Name":"NCC AB ser. A","Change":"+0.23%","Volume":411,"Open":219.90,"DaysLow":216.80,"DaysHigh":221.40,"LastTradePriceOnly":216.80,"LastTradeTime":"10:12am","LastTradeDate":"2/13/2017","Cap":"LargeCap"},{"Label":"NCC-B.ST","Name":"NCC AB ser. B","Change":"+0.18%","Volume":35544,"Open":217.00,"DaysLow":216.60,"DaysHigh":218.00,"LastTradePriceOnly":217.00,"LastTradeTime":"10:17am","LastTradeDate":"2/13/2017","Cap":"LargeCap"},{"Label":"NET-B.ST","Name":"NetEnt AB ser. B","Change":"+1.82%","Volume":177318,"Open":75.00,"DaysLow":74.65,"DaysHigh":75.80,"LastTradePriceOnly":75.65,"LastTradeTime":"10:18am","LastTradeDate":"2/13/2017","Cap":"LargeCap"},{"Label":"NIBE-B.ST","Name":"NIBE Industrier AB ser. B","Change":"-0.28%","Volume":147212,"Open":71.30,"DaysLow":70.75,"DaysHigh":71.30,"LastTradePriceOnly":71.05,"LastTradeTime":"10:18am","LastTradeDate":"2/13/2017","Cap":"LargeCap"},{"Label":"NOBI.ST","Name":"Nobia AB","Change":"+0.57%","Volume":43848,"Open":87.95,"DaysLow":87.25,"DaysHigh":88.10,"LastTradePriceOnly":88.10,"LastTradeTime":"10:15am","LastTradeDate":"2/13/2017","Cap":"LargeCap"},{"Label":"NDA-SEK.ST","Name":"Nordea Bank AB","Change":"+0.00%","Volume":840029,"Open":108.60,"DaysLow":108.20,"DaysHigh":108.70,"LastTradePriceOnly":108.40,"LastTradeTime":"10:17am","LastTradeDate":"2/13/2017","Cap":"LargeCap"},{"Label":"PNDX-B.ST","Name":"Pandox AB ser. B","Change":"-0.91%","Volume":3549,"Open":143.60,"DaysLow":140.90,"DaysHigh":143.60,"LastTradePriceOnly":141.10,"LastTradeTime":"10:15am","LastTradeDate":"2/13/2017","Cap":"LargeCap"},{"Label":"PEAB-B.ST","Name":"Peab AB ser. B","Change":"+1.37%","Volume":284191,"Open":79.95,"DaysLow":79.95,"DaysHigh":81.60,"LastTradePriceOnly":81.10,"LastTradeTime":"10:18am","LastTradeDate":"2/13/2017","Cap":"LargeCap"},{"Label":"RATO-A.ST","Name":"Ratos AB ser. A","Change":"+1.60%","Volume":1205,"Open":69.00,"DaysLow":69.00,"DaysHigh":70.00,"LastTradePriceOnly":70.00,"LastTradeTime":"10:12am","LastTradeDate":"2/13/2017","Cap":"LargeCap"},{"Label":"RATO-B.ST","Name":"Ratos AB ser. B","Change":"-0.46%","Volume":125609,"Open":48.27,"DaysLow":47.80,"DaysHigh":48.38,"LastTradePriceOnly":47.92,"LastTradeTime":"10:17am","LastTradeDate":"2/13/2017","Cap":"LargeCap"},{"Label":"RATO-PREF.ST","Name":"Ratos AB pref","Change":"+0.16%","Volume":3,"Open":1859.00,"DaysLow":1859.00,"DaysHigh":1861.00,"LastTradePriceOnly":1861.00,"LastTradeTime":"10:02am","LastTradeDate":"2/13/2017","Cap":"LargeCap"},{"Label":"RESURS.ST","Name":"Resurs Holding AB","Change":"+1.51%","Volume":155976,"Open":57.00,"DaysLow":56.40,"DaysHigh":57.25,"LastTradePriceOnly":57.25,"LastTradeTime":"10:18am","LastTradeDate":"2/13/2017","Cap":"LargeCap"},{"Label":"SAAB-B.ST","Name":"SAAB AB ser. B","Change":"-5.69%","Volume":357300,"Open":354.10,"DaysLow":341.10,"DaysHigh":359.10,"LastTradePriceOnly":344.80,"LastTradeTime":"10:18am","LastTradeDate":"2/13/2017","Cap":"LargeCap"},{"Label":"SAND.ST","Name":"Sandvik AB","Change":"-0.33%","Volume":621315,"Open":120.80,"DaysLow":119.70,"DaysHigh":121.00,"LastTradePriceOnly":120.10,"LastTradeTime":"10:17am","LastTradeDate":"2/13/2017","Cap":"LargeCap"},{"Label":"SCA-A.ST","Name":"Svenska Cellulosa AB SCA ser. A","Change":"+0.55%","Volume":673,"Open":276.00,"DaysLow":276.00,"DaysHigh":277.60,"LastTradePriceOnly":276.40,"LastTradeTime":"9:57am","LastTradeDate":"2/13/2017","Cap":"LargeCap"},{"Label":"SCA-B.ST","Name":"Svenska Cellulosa AB SCA ser. B","Change":"-0.18%","Volume":191612,"Open":270.90,"DaysLow":270.00,"DaysHigh":271.20,"LastTradePriceOnly":270.00,"LastTradeTime":"10:18am","LastTradeDate":"2/13/2017","Cap":"LargeCap"},{"Label":"SEB-A.ST","Name":"Skandinaviska Enskilda Banken s","Change":"+0.10%","Volume":843936,"Open":103.90,"DaysLow":103.20,"DaysHigh":103.90,"LastTradePriceOnly":103.60,"LastTradeTime":"10:17am","LastTradeDate":"2/13/2017","Cap":"LargeCap"},{"Label":"SEB-C.ST","Name":"Skandinaviska Enskilda Banken s","Change":"+0.68%","Volume":8324,"Open":105.00,"DaysLow":103.90,"DaysHigh":105.00,"LastTradePriceOnly":104.30,"LastTradeTime":"10:17am","LastTradeDate":"2/13/2017","Cap":"LargeCap"},{"Label":"SECU-B.ST","Name":"Securitas AB ser. B","Change":"+0.15%","Volume":137538,"Open":133.90,"DaysLow":133.20,"DaysHigh":134.10,"LastTradePriceOnly":133.70,"LastTradeTime":"10:17am","LastTradeDate":"2/13/2017","Cap":"LargeCap"},{"Label":"SKA-B.ST","Name":"Skanska AB ser. B","Change":"+0.37%","Volume":167537,"Open":217.00,"DaysLow":215.80,"DaysHigh":217.30,"LastTradePriceOnly":217.10,"LastTradeTime":"10:18am","LastTradeDate":"2/13/2017","Cap":"LargeCap"},{"Label":"SKF-A.ST","Name":"SKF, AB ser. A","Change":"+0.06%","Volume":13056,"Open":167.30,"DaysLow":167.30,"DaysHigh":168.70,"LastTradePriceOnly":167.40,"LastTradeTime":"10:10am","LastTradeDate":"2/13/2017","Cap":"LargeCap"},{"Label":"SKF-B.ST","Name":"SKF, AB ser. B","Change":"+0.06%","Volume":256838,"Open":168.20,"DaysLow":167.50,"DaysHigh":168.90,"LastTradePriceOnly":167.70,"LastTradeTime":"10:17am","LastTradeDate":"2/13/2017","Cap":"LargeCap"},{"Label":"SSAB-A.ST","Name":"SSAB AB ser. A","Change":"+0.78%","Volume":1508989,"Open":38.56,"DaysLow":38.51,"DaysHigh":39.22,"LastTradePriceOnly":38.66,"LastTradeTime":"10:18am","LastTradeDate":"2/13/2017","Cap":"LargeCap"},{"Label":"SSAB-B.ST","Name":"SSAB AB ser. B","Change":"+1.50%","Volume":1556637,"Open":31.50,"DaysLow":31.50,"DaysHigh":32.10,"LastTradePriceOnly":31.82,"LastTradeTime":"10:17am","LastTradeDate":"2/13/2017","Cap":"LargeCap"},{"Label":"STE-A.ST","Name":"Stora Enso Oyj ser. A","Change":"+0.75%","Volume":6199,"Open":99.90,"DaysLow":99.90,"DaysHigh":100.50,"LastTradePriceOnly":100.20,"LastTradeTime":"10:11am","LastTradeDate":"2/13/2017","Cap":"LargeCap"},{"Label":"STE-R.ST","Name":"Stora Enso Oyj ser. R","Change":"+1.12%","Volume":149552,"Open":94.50,"DaysLow":94.15,"DaysHigh":95.00,"LastTradePriceOnly":94.80,"LastTradeTime":"10:15am","LastTradeDate":"2/13/2017","Cap":"LargeCap"},{"Label":"SWEC-A.ST","Name":"SWECO AB ser. A","Change":"+0.00%","Volume":165,"Open":210.00,"DaysLow":209.90,"DaysHigh":210.00,"LastTradePriceOnly":210.00,"LastTradeTime":"9:46am","LastTradeDate":"2/13/2017","Cap":"LargeCap"},{"Label":"SWEC-B.ST","Name":"SWECO AB ser. B","Change":"+0.25%","Volume":11763,"Open":203.00,"DaysLow":202.40,"DaysHigh":203.30,"LastTradePriceOnly":203.10,"LastTradeTime":"10:18am","LastTradeDate":"2/13/2017","Cap":"LargeCap"},{"Label":"SWED-A.ST","Name":"Swedbank AB ser A","Change":"-0.53%","Volume":414746,"Open":227.90,"DaysLow":226.60,"DaysHigh":228.20,"LastTradePriceOnly":226.80,"LastTradeTime":"10:18am","LastTradeDate":"2/13/2017","Cap":"LargeCap"},{"Label":"SWMA.ST","Name":"Swedish Match AB","Change":"-0.55%","Volume":104426,"Open":289.90,"DaysLow":287.80,"DaysHigh":290.10,"LastTradePriceOnly":288.10,"LastTradeTime":"10:17am","LastTradeDate":"2/13/2017","Cap":"LargeCap"},{"Label":"SOBI.ST","Name":"Swedish Orphan Biovitrum AB","Change":"+0.17%","Volume":118551,"Open":117.50,"DaysLow":117.20,"DaysHigh":117.80,"LastTradePriceOnly":117.40,"LastTradeTime":"10:17am","LastTradeDate":"2/13/2017","Cap":"LargeCap"},{"Label":"TEL2-A.ST","Name":"Tele2 AB ser. A","Change":"+5.80%","Volume":10573,"Open":92.00,"DaysLow":92.00,"DaysHigh":96.85,"LastTradePriceOnly":95.70,"LastTradeTime":"10:17am","LastTradeDate":"2/13/2017","Cap":"LargeCap"},{"Label":"TEL2-B.ST","Name":"Tele2 AB ser. B","Change":"+0.97%","Volume":866276,"Open":77.95,"DaysLow":77.75,"DaysHigh":78.80,"LastTradePriceOnly":78.40,"LastTradeTime":"10:18am","LastTradeDate":"2/13/2017","Cap":"LargeCap"},{"Label":"TELIA.ST","Name":"Telia Company AB","Change":"+0.52%","Volume":1614974,"Open":34.95,"DaysLow":34.90,"DaysHigh":35.06,"LastTradePriceOnly":34.98,"LastTradeTime":"10:18am","LastTradeDate":"2/13/2017","Cap":"LargeCap"},{"Label":"TIEN.ST","Name":"Tieto Corporation","Change":"+0.17%","Volume":3330,"Open":242.30,"DaysLow":241.00,"DaysHigh":243.50,"LastTradePriceOnly":242.00,"LastTradeTime":"10:08am","LastTradeDate":"2/13/2017","Cap":"LargeCap"},{"Label":"TREL-B.ST","Name":"Trelleborg AB ser. B","Change":"+0.33%","Volume":96644,"Open":181.10,"DaysLow":180.40,"DaysHigh":181.30,"LastTradePriceOnly":181.20,"LastTradeTime":"10:17am","LastTradeDate":"2/13/2017","Cap":"LargeCap"},{"Label":"KIND-SDB.ST","Name":"KINDRED GROUP PLC","Change":"+0.65%","Volume":129760,"Open":76.80,"DaysLow":76.60,"DaysHigh":77.45,"LastTradePriceOnly":77.00,"LastTradeTime":"10:17am","LastTradeDate":"2/13/2017","Cap":"LargeCap"},{"Label":"VOLV-A.ST","Name":"Volvo, AB ser. A","Change":"+0.26%","Volume":43719,"Open":117.10,"DaysLow":117.10,"DaysHigh":117.60,"LastTradePriceOnly":117.30,"LastTradeTime":"10:16am","LastTradeDate":"2/13/2017","Cap":"LargeCap"},{"Label":"VOLV-B.ST","Name":"Volvo, AB ser. B","Change":"+0.43%","Volume":649998,"Open":117.30,"DaysLow":117.10,"DaysHigh":117.60,"LastTradePriceOnly":117.40,"LastTradeTime":"10:17am","LastTradeDate":"2/13/2017","Cap":"LargeCap"},{"Label":"WALL-B.ST","Name":"Wallenstam AB ser. B","Change":"-0.21%","Volume":13172,"Open":70.70,"DaysLow":70.45,"DaysHigh":70.95,"LastTradePriceOnly":70.55,"LastTradeTime":"10:15am","LastTradeDate":"2/13/2017","Cap":"LargeCap"},{"Label":"WIHL.ST","Name":"Wihlborgs Fastigheter AB","Change":"-1.03%","Volume":23088,"Open":172.60,"DaysLow":172.60,"DaysHigh":177.40,"LastTradePriceOnly":172.70,"LastTradeTime":"10:16am","LastTradeDate":"2/13/2017","Cap":"LargeCap"},{"Label":"ACAD.ST","Name":"AcadeMedia AB","Change":"+3.35%","Volume":63979,"Open":60.75,"DaysLow":60.75,"DaysHigh":62.25,"LastTradePriceOnly":61.75,"LastTradeTime":"10:17am","LastTradeDate":"2/13/2017","Cap":"MidCap"},{"Label":"ACTI.ST","Name":"Active Biotech AB","Change":"+0.00%","Volume":7647,"Open":12.55,"DaysLow":12.35,"DaysHigh":12.55,"LastTradePriceOnly":12.50,"LastTradeTime":"10:07am","LastTradeDate":"2/13/2017","Cap":"MidCap"},{"Label":"ALIF-B.ST","Name":"AddLife AB ser. B","Change":"+2.25%","Volume":121,"Open":158.50,"DaysLow":158.50,"DaysHigh":159.00,"LastTradePriceOnly":159.00,"LastTradeTime":"9:01am","LastTradeDate":"2/13/2017","Cap":"MidCap"},{"Label":"ADDT-B.ST","Name":"Addtech AB ser. B","Change":"-0.33%","Volume":2978,"Open":154.00,"DaysLow":152.00,"DaysHigh":155.00,"LastTradePriceOnly":152.50,"LastTradeTime":"10:12am","LastTradeDate":"2/13/2017","Cap":"MidCap"},{"Label":"AOI.ST","Name":"Africa Oil Corp.","Change":"-0.06%","Volume":475263,"Open":17.50,"DaysLow":17.34,"DaysHigh":17.60,"LastTradePriceOnly":17.45,"LastTradeTime":"10:18am","LastTradeDate":"2/13/2017","Cap":"MidCap"},{"Label":"ALIG.ST","Name":"Alimak Group AB","Change":"+0.39%","Volume":2379,"Open":130.00,"DaysLow":129.75,"DaysHigh":131.50,"LastTradePriceOnly":130.25,"LastTradeTime":"10:18am","LastTradeDate":"2/13/2017","Cap":"MidCap"},{"Label":"ATORX.ST","Name":"Alligator Bioscience AB","Change":"-0.31%","Volume":6356,"Open":33.00,"DaysLow":32.50,"DaysHigh":33.00,"LastTradePriceOnly":32.50,"LastTradeTime":"10:17am","LastTradeDate":"2/13/2017","Cap":"MidCap"},{"Label":"ARCM.ST","Name":"Arcam AB","Change":"+0.00%","Volume":304,"Open":318.00,"DaysLow":316.50,"DaysHigh":318.50,"LastTradePriceOnly":316.50,"LastTradeTime":"9:19am","LastTradeDate":"2/13/2017","Cap":"MidCap"},{"Label":"ATT.ST","Name":"Attendo AB","Change":"-0.64%","Volume":13262,"Open":85.60,"DaysLow":85.05,"DaysHigh":86.20,"LastTradePriceOnly":85.05,"LastTradeTime":"10:17am","LastTradeDate":"2/13/2017","Cap":"MidCap"},{"Label":"AZA.ST","Name":"Avanza Bank Holding AB","Change":"-0.35%","Volume":3281,"Open":400.00,"DaysLow":397.30,"DaysHigh":400.00,"LastTradePriceOnly":397.60,"LastTradeTime":"10:17am","LastTradeDate":"2/13/2017","Cap":"MidCap"},{"Label":"BBTO-B.ST","Name":"B&B TOOLS AB ser. B","Change":"-0.24%","Volume":4398,"Open":208.00,"DaysLow":204.00,"DaysHigh":208.00,"LastTradePriceOnly":205.50,"LastTradeTime":"10:11am","LastTradeDate":"2/13/2017","Cap":"MidCap"},{"Label":"BEIA-B.ST","Name":"Beijer Alma AB ser. B","Change":"-0.62%","Volume":1693,"Open":243.50,"DaysLow":240.00,"DaysHigh":243.50,"LastTradePriceOnly":242.00,"LastTradeTime":"10:16am","LastTradeDate":"2/13/2017","Cap":"MidCap"},{"Label":"BEIJ-B.ST","Name":"Beijer Ref AB ser. B","Change":"+0.47%","Volume":317,"Open":215.00,"DaysLow":213.50,"DaysHigh":215.00,"LastTradePriceOnly":214.50,"LastTradeTime":"9:59am","LastTradeDate":"2/13/2017","Cap":"MidCap"},{"Label":"BESQ.ST","Name":"Besqab AB","Change":"+0.24%","Volume":145,"Open":210.00,"DaysLow":206.50,"DaysHigh":210.00,"LastTradePriceOnly":206.50,"LastTradeTime":"9:53am","LastTradeDate":"2/13/2017","Cap":"MidCap"},{"Label":"BILI-A.ST","Name":"Bilia AB ser. A","Change":"+1.20%","Volume":28014,"Open":208.00,"DaysLow":207.50,"DaysHigh":210.00,"LastTradePriceOnly":210.00,"LastTradeTime":"10:14am","LastTradeDate":"2/13/2017","Cap":"MidCap"},{"Label":"BIOG-B.ST","Name":"BioGaia AB ser. B","Change":"+0.31%","Volume":3677,"Open":330.00,"DaysLow":327.00,"DaysHigh":333.00,"LastTradePriceOnly":328.00,"LastTradeTime":"10:16am","LastTradeDate":"2/13/2017","Cap":"MidCap"},{"Label":"PXXS-SDB.ST","Name":"BlackPearl Resources Inc. SDB","Change":"-1.46%","Volume":29870,"Open":10.25,"DaysLow":10.05,"DaysHigh":10.35,"LastTradePriceOnly":10.10,"LastTradeTime":"10:07am","LastTradeDate":"2/13/2017","Cap":"MidCap"},{"Label":"BRAV.ST","Name":"Bravida Holding AB","Change":"+0.00%","Volume":89711,"Open":58.60,"DaysLow":58.50,"DaysHigh":58.75,"LastTradePriceOnly":58.50,"LastTradeTime":"10:13am","LastTradeDate":"2/13/2017","Cap":"MidCap"},{"Label":"BUFAB.ST","Name":"Bufab AB","Change":"+1.27%","Volume":5010,"Open":79.00,"DaysLow":79.00,"DaysHigh":80.00,"LastTradePriceOnly":80.00,"LastTradeTime":"9:46am","LastTradeDate":"2/13/2017","Cap":"MidCap"},{"Label":"BULTEN.ST","Name":"Bulten AB","Change":"-0.24%","Volume":2967,"Open":102.50,"DaysLow":101.25,"DaysHigh":102.50,"LastTradePriceOnly":102.25,"LastTradeTime":"9:56am","LastTradeDate":"2/13/2017","Cap":"MidCap"},{"Label":"BURE.ST","Name":"Bure Equity AB","Change":"+1.41%","Volume":22391,"Open":106.25,"DaysLow":106.25,"DaysHigh":107.75,"LastTradePriceOnly":107.75,"LastTradeTime":"10:17am","LastTradeDate":"2/13/2017","Cap":"MidCap"},{"Label":"BMAX.ST","Name":"Byggmax Group AB","Change":"-0.43%","Volume":26487,"Open":58.75,"DaysLow":58.00,"DaysHigh":59.00,"LastTradePriceOnly":58.50,"LastTradeTime":"10:15am","LastTradeDate":"2/13/2017","Cap":"MidCap"},{"Label":"CAMX.ST","Name":"Camurus AB","Change":"-0.66%","Volume":2871,"Open":113.00,"DaysLow":112.50,"DaysHigh":114.75,"LastTradePriceOnly":112.50,"LastTradeTime":"10:12am","LastTradeDate":"2/13/2017","Cap":"MidCap"},{"Label":"CAPIO.ST","Name":"Capio AB","Change":"-1.08%","Volume":46808,"Open":45.90,"DaysLow":45.80,"DaysHigh":46.30,"LastTradePriceOnly":45.80,"LastTradeTime":"10:14am","LastTradeDate":"2/13/2017","Cap":"MidCap"},{"Label":"CATE.ST","Name":"Catena AB","Change":"+0.55%","Volume":1606,"Open":136.00,"DaysLow":135.00,"DaysHigh":136.25,"LastTradePriceOnly":136.25,"LastTradeTime":"10:16am","LastTradeDate":"2/13/2017","Cap":"MidCap"},{"Label":"CCC.ST","Name":"Cavotec SA","Change":"+1.36%","Volume":2325,"Open":22.50,"DaysLow":22.40,"DaysHigh":22.50,"LastTradePriceOnly":22.40,"LastTradeTime":"10:08am","LastTradeDate":"2/13/2017","Cap":"MidCap"},{"Label":"CLAS-B.ST","Name":"Clas Ohlson AB ser. B","Change":"+0.55%","Volume":10503,"Open":136.00,"DaysLow":136.00,"DaysHigh":136.75,"LastTradePriceOnly":136.50,"LastTradeTime":"10:17am","LastTradeDate":"2/13/2017","Cap":"MidCap"},{"Label":"CLA-B.ST","Name":"Cloetta AB ser. B","Change":"-0.68%","Volume":57141,"Open":29.10,"DaysLow":28.90,"DaysHigh":29.20,"LastTradePriceOnly":29.10,"LastTradeTime":"10:18am","LastTradeDate":"2/13/2017","Cap":"MidCap"},{"Label":"CLX.ST","Name":"CLX Communications AB","Change":"-0.55%","Volume":3737,"Open":91.00,"DaysLow":90.75,"DaysHigh":91.75,"LastTradePriceOnly":90.75,"LastTradeTime":"10:07am","LastTradeDate":"2/13/2017","Cap":"MidCap"},{"Label":"COLL.ST","Name":"Collector AB","Change":"-1.14%","Volume":3188,"Open":105.00,"DaysLow":101.20,"DaysHigh":105.00,"LastTradePriceOnly":103.70,"LastTradeTime":"10:15am","LastTradeDate":"2/13/2017","Cap":"MidCap"},{"Label":"COIC.ST","Name":"Concentric AB","Change":"-0.21%","Volume":1877,"Open":120.50,"DaysLow":120.50,"DaysHigh":121.50,"LastTradePriceOnly":121.50,"LastTradeTime":"10:17am","LastTradeDate":"2/13/2017","Cap":"MidCap"},{"Label":"COOR.ST","Name":"Coor Service Management Holding","Change":"+0.89%","Volume":2915,"Open":57.50,"DaysLow":56.25,"DaysHigh":57.50,"LastTradePriceOnly":56.50,"LastTradeTime":"10:09am","LastTradeDate":"2/13/2017","Cap":"MidCap"},{"Label":"CORE.ST","Name":"Corem Property Group AB","Change":"+0.26%","Volume":206,"Open":38.30,"DaysLow":38.30,"DaysHigh":38.30,"LastTradePriceOnly":38.30,"LastTradeTime":"9:08am","LastTradeDate":"2/13/2017","Cap":"MidCap"},{"Label":"CORE-PREF.ST","Name":"Corem Property Group AB Pref","Change":"+0.00%","Volume":84,"Open":139.50,"DaysLow":139.50,"DaysHigh":139.50,"LastTradePriceOnly":139.50,"LastTradeTime":"9:26am","LastTradeDate":"2/13/2017","Cap":"MidCap"},{"Label":"CRED-A.ST","Name":"Creades AB A","Change":"+0.71%","Volume":1643,"Open":286.00,"DaysLow":280.50,"DaysHigh":286.00,"LastTradePriceOnly":282.00,"LastTradeTime":"10:05am","LastTradeDate":"2/13/2017","Cap":"MidCap"},{"Label":"DCAR-B.ST","Name":"D. Carnegie & Co AB B","Change":"-0.22%","Volume":8121,"Open":113.00,"DaysLow":111.00,"DaysHigh":113.00,"LastTradePriceOnly":111.25,"LastTradeTime":"10:17am","LastTradeDate":"2/13/2017","Cap":"MidCap"},{"Label":"DIOS.ST","Name":"Dis Fastigheter AB","Change":"+0.00%","Volume":81151,"Open":44.70,"DaysLow":44.40,"DaysHigh":45.00,"LastTradePriceOnly":44.60,"LastTradeTime":"10:18am","LastTradeDate":"2/13/2017","Cap":"MidCap"},{"Label":"DUNI.ST","Name":"Duni AB","Change":"+0.80%","Volume":5573,"Open":124.00,"DaysLow":124.00,"DaysHigh":126.50,"LastTradePriceOnly":125.50,"LastTradeTime":"10:16am","LastTradeDate":"2/13/2017","Cap":"MidCap"},{"Label":"DUST.ST","Name":"Dustin Group AB","Change":"-0.37%","Volume":8348,"Open":66.75,"DaysLow":66.50,"DaysHigh":67.00,"LastTradePriceOnly":66.50,"LastTradeTime":"9:53am","LastTradeDate":"2/13/2017","Cap":"MidCap"},{"Label":"ECEX.ST","Name":"East Capital Explorer AB","Change":"+4.85%","Volume":31361,"Open":68.50,"DaysLow":68.50,"DaysHigh":70.75,"LastTradePriceOnly":70.25,"LastTradeTime":"10:15am","LastTradeDate":"2/13/2017","Cap":"MidCap"},{"Label":"ELTEL.ST","Name":"Eltel AB","Change":"+1.93%","Volume":50763,"Open":49.30,"DaysLow":49.30,"DaysHigh":50.25,"LastTradePriceOnly":50.25,"LastTradeTime":"10:15am","LastTradeDate":"2/13/2017","Cap":"MidCap"},{"Label":"ENQ.ST","Name":"EnQuest PLC","Change":"+6.70%","Volume":3566883,"Open":5.33,"DaysLow":5.33,"DaysHigh":5.65,"LastTradePriceOnly":5.65,"LastTradeTime":"10:18am","LastTradeDate":"2/13/2017","Cap":"MidCap"},{"Label":"FAG.ST","Name":"Fagerhult, AB","Change":"+0.36%","Volume":475,"Open":276.00,"DaysLow":276.00,"DaysHigh":279.50,"LastTradePriceOnly":277.00,"LastTradeTime":"10:05am","LastTradeDate":"2/13/2017","Cap":"MidCap"},{"Label":"FPAR.ST","Name":"Fast Partner AB","Change":"+1.49%","Volume":124,"Open":136.00,"DaysLow":136.00,"DaysHigh":136.75,"LastTradePriceOnly":136.00,"LastTradeTime":"9:49am","LastTradeDate":"2/13/2017","Cap":"MidCap"},{"Label":"FPAR-PREF.ST","Name":"Fast Partner AB Pref","Change":"+0.00%","Volume":0,"Open":333.50,"DaysLow":333.50,"DaysHigh":333.50,"LastTradePriceOnly":333.50,"LastTradeTime":"5:29pm","LastTradeDate":"2/10/2017","Cap":"MidCap"},{"Label":"FOI-B.ST","Name":"Fenix Outdoor International AG ","Change":"+0.12%","Volume":403,"Open":800.00,"DaysLow":800.00,"DaysHigh":815.00,"LastTradePriceOnly":805.00,"LastTradeTime":"10:17am","LastTradeDate":"2/13/2017","Cap":"MidCap"},{"Label":"GRNG.ST","Name":"Grnges AB","Change":"+1.52%","Volume":90422,"Open":83.00,"DaysLow":82.50,"DaysHigh":83.75,"LastTradePriceOnly":83.75,"LastTradeTime":"10:18am","LastTradeDate":"2/13/2017","Cap":"MidCap"},{"Label":"GUNN.ST","Name":"Gunnebo AB","Change":"-0.68%","Volume":6431,"Open":44.00,"DaysLow":42.90,"DaysHigh":44.10,"LastTradePriceOnly":44.00,"LastTradeTime":"10:17am","LastTradeDate":"2/13/2017","Cap":"MidCap"},{"Label":"HLDX.ST","Name":"Haldex AB","Change":"-0.64%","Volume":7737,"Open":116.00,"DaysLow":116.00,"DaysHigh":116.25,"LastTradePriceOnly":116.00,"LastTradeTime":"9:55am","LastTradeDate":"2/13/2017","Cap":"MidCap"},{"Label":"HEBA-B.ST","Name":"Heba Fastighets AB ser. B","Change":"+0.00%","Volume":120,"Open":111.25,"DaysLow":111.25,"DaysHigh":111.50,"LastTradePriceOnly":111.25,"LastTradeTime":"9:31am","LastTradeDate":"2/13/2017","Cap":"MidCap"},{"Label":"HEMF.ST","Name":"Hemfosa Fastigheter AB","Change":"+0.18%","Volume":121909,"Open":84.80,"DaysLow":84.60,"DaysHigh":85.00,"LastTradePriceOnly":84.75,"LastTradeTime":"10:18am","LastTradeDate":"2/13/2017","Cap":"MidCap"},{"Label":"HEMF-PREF.ST","Name":"Hemfosa Fastigheter Pref AB","Change":"+0.06%","Volume":2033,"Open":157.90,"DaysLow":157.20,"DaysHigh":158.00,"LastTradePriceOnly":158.00,"LastTradeTime":"10:10am","LastTradeDate":"2/13/2017","Cap":"MidCap"},{"Label":"HIQ.ST","Name":"HiQ International AB","Change":"+0.00%","Volume":18816,"Open":65.25,"DaysLow":64.00,"DaysHigh":65.50,"LastTradePriceOnly":65.00,"LastTradeTime":"10:17am","LastTradeDate":"2/13/2017","Cap":"MidCap"},{"Label":"HMS.ST","Name":"HMS Networks AB","Change":"+2.80%","Volume":746,"Open":357.00,"DaysLow":357.00,"DaysHigh":367.00,"LastTradePriceOnly":367.00,"LastTradeTime":"10:15am","LastTradeDate":"2/13/2017","Cap":"MidCap"},{"Label":"HOFI.ST","Name":"Hoist Finance AB","Change":"-1.57%","Volume":45539,"Open":79.50,"DaysLow":78.00,"DaysHigh":79.50,"LastTradePriceOnly":78.25,"LastTradeTime":"10:18am","LastTradeDate":"2/13/2017","Cap":"MidCap"},{"Label":"HUM.ST","Name":"Humana AB","Change":"+0.32%","Volume":18123,"Open":78.75,"DaysLow":78.25,"DaysHigh":79.00,"LastTradePriceOnly":79.00,"LastTradeTime":"10:17am","LastTradeDate":"2/13/2017","Cap":"MidCap"},{"Label":"ENG.ST","Name":"Internationella Engelska Skolan","Change":"-0.36%","Volume":9716,"Open":67.75,"DaysLow":67.75,"DaysHigh":68.50,"LastTradePriceOnly":68.25,"LastTradeTime":"10:09am","LastTradeDate":"2/13/2017","Cap":"MidCap"},{"Label":"IVSO.ST","Name":"Invisio Communications AB","Change":"-0.72%","Volume":5353,"Open":69.00,"DaysLow":68.75,"DaysHigh":69.75,"LastTradePriceOnly":68.75,"LastTradeTime":"10:13am","LastTradeDate":"2/13/2017","Cap":"MidCap"},{"Label":"INWI.ST","Name":"Inwido AB","Change":"-0.91%","Volume":19764,"Open":110.25,"DaysLow":109.25,"DaysHigh":110.75,"LastTradePriceOnly":109.25,"LastTradeTime":"10:16am","LastTradeDate":"2/13/2017","Cap":"MidCap"},{"Label":"ITAB-B.ST","Name":"ITAB Shop Concept AB ser. B","Change":"+0.00%","Volume":3525,"Open":78.75,"DaysLow":78.00,"DaysHigh":79.00,"LastTradePriceOnly":78.75,"LastTradeTime":"10:11am","LastTradeDate":"2/13/2017","Cap":"MidCap"},{"Label":"KAHL.ST","Name":"KappAhl AB","Change":"-1.44%","Volume":15285,"Open":52.00,"DaysLow":51.00,"DaysHigh":52.25,"LastTradePriceOnly":51.25,"LastTradeTime":"10:16am","LastTradeDate":"2/13/2017","Cap":"MidCap"},{"Label":"KLED.ST","Name":"Kungsleden AB","Change":"-0.64%","Volume":34736,"Open":55.00,"DaysLow":54.55,"DaysHigh":55.10,"LastTradePriceOnly":54.65,"LastTradeTime":"10:12am","LastTradeDate":"2/13/2017","Cap":"MidCap"},{"Label":"LAGR-B.ST","Name":"Lagercrantz Group AB ser B","Change":"+2.11%","Volume":8899,"Open":83.50,"DaysLow":83.50,"DaysHigh":84.75,"LastTradePriceOnly":84.75,"LastTradeTime":"10:17am","LastTradeDate":"2/13/2017","Cap":"MidCap"},{"Label":"LIAB.ST","Name":"Lindab International AB","Change":"-2.50%","Volume":21945,"Open":74.05,"DaysLow":74.05,"DaysHigh":75.50,"LastTradePriceOnly":74.10,"LastTradeTime":"10:12am","LastTradeDate":"2/13/2017","Cap":"MidCap"},{"Label":"LUC.ST","Name":"Lucara Diamond Corp","Change":"-0.47%","Volume":42130,"Open":21.50,"DaysLow":21.30,"DaysHigh":21.50,"LastTradePriceOnly":21.30,"LastTradeTime":"10:16am","LastTradeDate":"2/13/2017","Cap":"MidCap"},{"Label":"LUG.ST","Name":"Lundin Gold Inc.","Change":"+0.51%","Volume":8155,"Open":39.40,"DaysLow":39.40,"DaysHigh":39.60,"LastTradePriceOnly":39.60,"LastTradeTime":"10:17am","LastTradeDate":"2/13/2017","Cap":"MidCap"},{"Label":"MVIR-B.ST","Name":"Medivir AB ser. B","Change":"+0.32%","Volume":5426,"Open":79.50,"DaysLow":78.25,"DaysHigh":79.50,"LastTradePriceOnly":79.00,"LastTradeTime":"10:14am","LastTradeDate":"2/13/2017","Cap":"MidCap"},{"Label":"MEKO.ST","Name":"Mekonomen AB","Change":"+0.57%","Volume":3039,"Open":177.00,"DaysLow":175.50,"DaysHigh":177.00,"LastTradePriceOnly":177.00,"LastTradeTime":"9:58am","LastTradeDate":"2/13/2017","Cap":"MidCap"},{"Label":"MUNK1S.ST","Name":"Munksj Oyj","Change":"+0.00%","Volume":490,"Open":136.25,"DaysLow":136.25,"DaysHigh":138.00,"LastTradePriceOnly":138.00,"LastTradeTime":"9:29am","LastTradeDate":"2/13/2017","Cap":"MidCap"},{"Label":"MYCR.ST","Name":"Mycronic AB","Change":"-2.30%","Volume":126734,"Open":109.00,"DaysLow":105.25,"DaysHigh":109.25,"LastTradePriceOnly":106.00,"LastTradeTime":"10:15am","LastTradeDate":"2/13/2017","Cap":"MidCap"},{"Label":"NMAN.ST","Name":"Nederman Holding AB","Change":"+2.96%","Volume":328,"Open":220.00,"DaysLow":220.00,"DaysHigh":226.00,"LastTradePriceOnly":226.00,"LastTradeTime":"9:41am","LastTradeDate":"2/13/2017","Cap":"MidCap"},{"Label":"NEWA-B.ST","Name":"New Wave Group AB ser. B","Change":"+1.69%","Volume":35026,"Open":60.25,"DaysLow":60.00,"DaysHigh":60.50,"LastTradePriceOnly":60.25,"LastTradeTime":"10:17am","LastTradeDate":"2/13/2017","Cap":"MidCap"},{"Label":"NGQ.ST","Name":"NGEx Resources Inc","Change":"+1.69%","Volume":76736,"Open":8.90,"DaysLow":8.90,"DaysHigh":9.05,"LastTradePriceOnly":9.00,"LastTradeTime":"10:10am","LastTradeDate":"2/13/2017","Cap":"MidCap"},{"Label":"NOBINA.ST","Name":"Nobina AB","Change":"+0.45%","Volume":16450,"Open":55.50,"DaysLow":55.50,"DaysHigh":55.75,"LastTradePriceOnly":55.75,"LastTradeTime":"10:16am","LastTradeDate":"2/13/2017","Cap":"MidCap"},{"Label":"NOLA-B.ST","Name":"Nolato AB ser. B","Change":"+1.32%","Volume":3736,"Open":265.00,"DaysLow":264.00,"DaysHigh":268.50,"LastTradePriceOnly":268.00,"LastTradeTime":"10:15am","LastTradeDate":"2/13/2017","Cap":"MidCap"},{"Label":"NDX.ST","Name":"Nordax Group AB","Change":"-0.99%","Volume":324544,"Open":49.80,"DaysLow":48.00,"DaysHigh":50.50,"LastTradePriceOnly":50.25,"LastTradeTime":"10:18am","LastTradeDate":"2/13/2017","Cap":"MidCap"},{"Label":"NWG.ST","Name":"Nordic Waterproofing Holding A/","Change":"+1.32%","Volume":11571,"Open":94.25,"DaysLow":94.25,"DaysHigh":96.00,"LastTradePriceOnly":96.00,"LastTradeTime":"10:09am","LastTradeDate":"2/13/2017","Cap":"MidCap"},{"Label":"NN-B.ST","Name":"Nordnet AB ser. B","Change":"-0.26%","Volume":551,"Open":38.00,"DaysLow":37.90,"DaysHigh":38.00,"LastTradePriceOnly":37.90,"LastTradeTime":"9:34am","LastTradeDate":"2/13/2017","Cap":"MidCap"},{"Label":"NP3.ST","Name":"NP3 Fastigheter AB","Change":"+0.41%","Volume":3577,"Open":48.20,"DaysLow":47.70,"DaysHigh":48.40,"LastTradePriceOnly":48.40,"LastTradeTime":"10:16am","LastTradeDate":"2/13/2017","Cap":"MidCap"},{"Label":"OASM.ST","Name":"Oasmia Pharmaceutical AB","Change":"+0.00%","Volume":61978,"Open":7.60,"DaysLow":7.40,"DaysHigh":7.60,"LastTradePriceOnly":7.40,"LastTradeTime":"10:17am","LastTradeDate":"2/13/2017","Cap":"MidCap"},{"Label":"OEM-B.ST","Name":"OEM International AB ser. B","Change":"+0.64%","Volume":351,"Open":156.00,"DaysLow":156.00,"DaysHigh":158.50,"LastTradePriceOnly":156.50,"LastTradeTime":"9:58am","LastTradeDate":"2/13/2017","Cap":"MidCap"},{"Label":"OPUS.ST","Name":"Opus Group AB","Change":"+1.27%","Volume":395274,"Open":7.90,"DaysLow":7.85,"DaysHigh":8.00,"LastTradePriceOnly":7.95,"LastTradeTime":"10:18am","LastTradeDate":"2/13/2017","Cap":"MidCap"},{"Label":"ORX.ST","Name":"Orexo AB","Change":"-0.90%","Volume":53531,"Open":33.30,"DaysLow":32.80,"DaysHigh":33.60,"LastTradePriceOnly":33.00,"LastTradeTime":"10:18am","LastTradeDate":"2/13/2017","Cap":"MidCap"},{"Label":"ORI.ST","Name":"Oriflame Holding AG","Change":"+1.64%","Volume":5065,"Open":280.00,"DaysLow":280.00,"DaysHigh":285.40,"LastTradePriceOnly":284.50,"LastTradeTime":"10:17am","LastTradeDate":"2/13/2017","Cap":"MidCap"},{"Label":"PLAZ-B.ST","Name":"Platzer Fastigheter Holding AB ","Change":"+0.21%","Volume":1083,"Open":47.40,"DaysLow":47.40,"DaysHigh":47.50,"LastTradePriceOnly":47.40,"LastTradeTime":"10:04am","LastTradeDate":"2/13/2017","Cap":"MidCap"},{"Label":"QLRO.ST","Name":"Qliro Group AB","Change":"-0.41%","Volume":60758,"Open":12.15,"DaysLow":11.95,"DaysHigh":12.15,"LastTradePriceOnly":12.10,"LastTradeTime":"10:13am","LastTradeDate":"2/13/2017","Cap":"MidCap"},{"Label":"RAY-B.ST","Name":"RaySearch Laboratories AB ser. ","Change":"+0.68%","Volume":1561,"Open":221.50,"DaysLow":220.00,"DaysHigh":222.50,"LastTradePriceOnly":222.50,"LastTradeTime":"10:15am","LastTradeDate":"2/13/2017","Cap":"MidCap"},{"Label":"RECI-B.ST","Name":"Recipharm AB","Change":"-0.83%","Volume":5441,"Open":120.00,"DaysLow":119.00,"DaysHigh":120.75,"LastTradePriceOnly":119.00,"LastTradeTime":"10:10am","LastTradeDate":"2/13/2017","Cap":"MidCap"},{"Label":"REZT.ST","Name":"Rezidor Hotel Group AB","Change":"+0.00%","Volume":25722,"Open":34.90,"DaysLow":34.90,"DaysHigh":35.00,"LastTradePriceOnly":34.90,"LastTradeTime":"10:09am","LastTradeDate":"2/13/2017","Cap":"MidCap"},{"Label":"SAGA-A.ST","Name":"Sagax AB A","Change":"+1.45%","Volume":690,"Open":85.90,"DaysLow":85.90,"DaysHigh":87.20,"LastTradePriceOnly":87.20,"LastTradeTime":"10:16am","LastTradeDate":"2/13/2017","Cap":"MidCap"},{"Label":"SAGA-B.ST","Name":"Sagax AB B","Change":"+0.70%","Volume":2984,"Open":86.00,"DaysLow":85.95,"DaysHigh":86.95,"LastTradePriceOnly":86.10,"LastTradeTime":"10:06am","LastTradeDate":"2/13/2017","Cap":"MidCap"},{"Label":"SAGA-D.ST","Name":"Sagax AB D","Change":"+0.04%","Volume":1077,"Open":27.60,"DaysLow":27.60,"DaysHigh":27.61,"LastTradePriceOnly":27.61,"LastTradeTime":"9:50am","LastTradeDate":"2/13/2017","Cap":"MidCap"},{"Label":"SAGA-PREF.ST","Name":"Sagax AB pref","Change":"+0.57%","Volume":8674,"Open":30.06,"DaysLow":30.06,"DaysHigh":30.27,"LastTradePriceOnly":30.25,"LastTradeTime":"10:17am","LastTradeDate":"2/13/2017","Cap":"MidCap"},{"Label":"SAS.ST","Name":"SAS AB","Change":"+0.69%","Volume":44145,"Open":14.50,"DaysLow":14.50,"DaysHigh":14.70,"LastTradePriceOnly":14.60,"LastTradeTime":"10:13am","LastTradeDate":"2/13/2017","Cap":"MidCap"},{"Label":"SAS-PREF.ST","Name":"SAS AB PREF","Change":"+0.19%","Volume":1227,"Open":532.00,"DaysLow":531.00,"DaysHigh":533.00,"LastTradePriceOnly":533.00,"LastTradeTime":"10:15am","LastTradeDate":"2/13/2017","Cap":"MidCap"},{"Label":"SCST.ST","Name":"Scandi Standard AB","Change":"+0.00%","Volume":11777,"Open":54.75,"DaysLow":54.25,"DaysHigh":54.75,"LastTradePriceOnly":54.75,"LastTradeTime":"10:16am","LastTradeDate":"2/13/2017","Cap":"MidCap"},{"Label":"SHOT.ST","Name":"Scandic Hotels Group AB","Change":"-0.63%","Volume":51141,"Open":78.75,"DaysLow":78.25,"DaysHigh":78.75,"LastTradePriceOnly":78.25,"LastTradeTime":"10:14am","LastTradeDate":"2/13/2017","Cap":"MidCap"},{"Label":"SECT-B.ST","Name":"SECTRA AB ser B","Change":"+0.65%","Volume":5894,"Open":155.00,"DaysLow":153.50,"DaysHigh":156.00,"LastTradePriceOnly":156.00,"LastTradeTime":"10:17am","LastTradeDate":"2/13/2017","Cap":"MidCap"},{"Label":"SMF.ST","Name":"Semafo Inc.","Change":"-0.51%","Volume":12162,"Open":33.40,"DaysLow":33.00,"DaysHigh":33.40,"LastTradePriceOnly":33.29,"LastTradeTime":"10:17am","LastTradeDate":"2/13/2017","Cap":"MidCap"},{"Label":"SENS.ST","Name":"Sensys Gatso Group AB","Change":"+4.10%","Volume":1959752,"Open":1.27,"DaysLow":1.26,"DaysHigh":1.32,"LastTradePriceOnly":1.27,"LastTradeTime":"10:15am","LastTradeDate":"2/13/2017","Cap":"MidCap"},{"Label":"SRNKE-B.ST","Name":"Serneke Group AB B","Change":"+0.00%","Volume":3774,"Open":103.00,"DaysLow":102.75,"DaysHigh":103.50,"LastTradePriceOnly":103.00,"LastTradeTime":"10:17am","LastTradeDate":"2/13/2017","Cap":"MidCap"},{"Label":"SKIS-B.ST","Name":"SkiStar AB ser. B","Change":"+0.32%","Volume":2149,"Open":156.00,"DaysLow":156.00,"DaysHigh":157.00,"LastTradePriceOnly":156.50,"LastTradeTime":"9:51am","LastTradeDate":"2/13/2017","Cap":"MidCap"},{"Label":"SYSR.ST","Name":"Systemair AB","Change":"-0.39%","Volume":528,"Open":128.00,"DaysLow":127.50,"DaysHigh":128.00,"LastTradePriceOnly":127.50,"LastTradeTime":"9:52am","LastTradeDate":"2/13/2017","Cap":"MidCap"},{"Label":"TETY.ST","Name":"Tethys Oil AB","Change":"+0.33%","Volume":15624,"Open":75.00,"DaysLow":74.00,"DaysHigh":75.25,"LastTradePriceOnly":75.25,"LastTradeTime":"10:02am","LastTradeDate":"2/13/2017","Cap":"MidCap"},{"Label":"TFBANK.ST","Name":"TF Bank AB","Change":"+1.52%","Volume":27025,"Open":99.00,"DaysLow":99.00,"DaysHigh":100.50,"LastTradePriceOnly":100.50,"LastTradeTime":"10:12am","LastTradeDate":"2/13/2017","Cap":"MidCap"},{"Label":"THULE.ST","Name":"Thule Group AB","Change":"-0.74%","Volume":34825,"Open":149.00,"DaysLow":147.70,"DaysHigh":149.90,"LastTradePriceOnly":147.80,"LastTradeTime":"10:18am","LastTradeDate":"2/13/2017","Cap":"MidCap"},{"Label":"TOBII.ST","Name":"Tobii AB","Change":"+4.65%","Volume":301761,"Open":65.75,"DaysLow":65.50,"DaysHigh":67.50,"LastTradePriceOnly":67.50,"LastTradeTime":"10:18am","LastTradeDate":"2/13/2017","Cap":"MidCap"},{"Label":"TRAC-B.ST","Name":"Traction AB ser. B","Change":"+1.93%","Volume":382,"Open":184.50,"DaysLow":184.50,"DaysHigh":187.50,"LastTradePriceOnly":184.50,"LastTradeTime":"10:13am","LastTradeDate":"2/13/2017","Cap":"MidCap"},{"Label":"TWW.ST","Name":"Transcom WorldWide AB","Change":"+0.00%","Volume":54,"Open":87.25,"DaysLow":87.25,"DaysHigh":87.25,"LastTradePriceOnly":87.25,"LastTradeTime":"9:00am","LastTradeDate":"2/13/2017","Cap":"MidCap"},{"Label":"TROAX.ST","Name":"Troax Group AB","Change":"+0.51%","Volume":2709,"Open":193.50,"DaysLow":193.50,"DaysHigh":197.00,"LastTradePriceOnly":196.00,"LastTradeTime":"10:17am","LastTradeDate":"2/13/2017","Cap":"MidCap"},{"Label":"VBG-B.ST","Name":"VBG GROUP AB ser. B","Change":"-1.82%","Volume":9507,"Open":123.00,"DaysLow":121.00,"DaysHigh":123.00,"LastTradePriceOnly":121.25,"LastTradeTime":"10:08am","LastTradeDate":"2/13/2017","Cap":"MidCap"},{"Label":"VICP-A.ST","Name":"Victoria Park AB ser. A","Change":"+2.04%","Volume":15055,"Open":24.50,"DaysLow":24.40,"DaysHigh":25.00,"LastTradePriceOnly":25.00,"LastTradeTime":"10:04am","LastTradeDate":"2/13/2017","Cap":"MidCap"},{"Label":"VICP-B.ST","Name":"Victoria Park AB ser. B","Change":"+1.63%","Volume":43289,"Open":24.80,"DaysLow":24.60,"DaysHigh":25.00,"LastTradePriceOnly":25.00,"LastTradeTime":"10:18am","LastTradeDate":"2/13/2017","Cap":"MidCap"},{"Label":"VICP-PREF.ST","Name":"Victoria Park AB Pref","Change":"-0.53%","Volume":1398,"Open":281.00,"DaysLow":281.00,"DaysHigh":281.50,"LastTradePriceOnly":281.50,"LastTradeTime":"9:19am","LastTradeDate":"2/13/2017","Cap":"MidCap"},{"Label":"VITR.ST","Name":"Vitrolife AB","Change":"+3.51%","Volume":7455,"Open":460.00,"DaysLow":460.00,"DaysHigh":474.50,"LastTradePriceOnly":472.00,"LastTradeTime":"10:18am","LastTradeDate":"2/13/2017","Cap":"MidCap"},{"Label":"VNV-SDB.ST","Name":"Vostok New Ventures Ltd","Change":"-1.02%","Volume":1218,"Open":72.25,"DaysLow":72.25,"DaysHigh":74.25,"LastTradePriceOnly":73.00,"LastTradeTime":"10:05am","LastTradeDate":"2/13/2017","Cap":"MidCap"},{"Label":"WTX.ST","Name":"Wilson Therapeutics AB","Change":"-0.49%","Volume":89,"Open":51.50,"DaysLow":50.75,"DaysHigh":51.50,"LastTradePriceOnly":50.75,"LastTradeTime":"9:38am","LastTradeDate":"2/13/2017","Cap":"MidCap"},{"Label":"XVIVO.ST","Name":"Xvivo Perfusion AB","Change":"-0.58%","Volume":4962,"Open":86.00,"DaysLow":86.00,"DaysHigh":87.00,"LastTradePriceOnly":86.25,"LastTradeTime":"10:04am","LastTradeDate":"2/13/2017","Cap":"MidCap"},{"Label":"AF-B.ST","Name":"F AB ser. B","Change":"+0.28%","Volume":8673,"Open":181.00,"DaysLow":178.40,"DaysHigh":181.60,"LastTradePriceOnly":179.00,"LastTradeTime":"10:09am","LastTradeDate":"2/13/2017","Cap":"MidCap"},{"Label":"ORES.ST","Name":"resund, Investment AB","Change":"-0.65%","Volume":9846,"Open":154.00,"DaysLow":152.00,"DaysHigh":154.00,"LastTradePriceOnly":152.00,"LastTradeTime":"10:11am","LastTradeDate":"2/13/2017","Cap":"MidCap"},{"Label":"ACAN-B.ST","Name":"Acando AB ser. B","Change":"-0.31%","Volume":66244,"Open":32.00,"DaysLow":31.70,"DaysHigh":32.00,"LastTradePriceOnly":31.80,"LastTradeTime":"10:17am","LastTradeDate":"2/13/2017","Cap":"SmallCap"},{"Label":"ANOD-B.ST","Name":"Addnode Group AB ser. B","Change":"+1.22%","Volume":2063,"Open":61.75,"DaysLow":61.25,"DaysHigh":62.00,"LastTradePriceOnly":62.00,"LastTradeTime":"9:51am","LastTradeDate":"2/13/2017","Cap":"SmallCap"},{"Label":"ATEL-A.ST","Name":"AllTele Allmnna Svenska Telefon","Change":"+0.53%","Volume":7900,"Open":19.00,"DaysLow":19.00,"DaysHigh":19.10,"LastTradePriceOnly":19.10,"LastTradeTime":"9:26am","LastTradeDate":"2/13/2017","Cap":"SmallCap"},{"Label":"ANOT.ST","Name":"Anoto Group AB","Change":"+0.641%","Volume":2751858,"Open":0.155,"DaysLow":0.155,"DaysHigh":0.158,"LastTradePriceOnly":0.157,"LastTradeTime":"10:11am","LastTradeDate":"2/13/2017","Cap":"SmallCap"},{"Label":"ARP.ST","Name":"Arctic Paper S.A.","Change":"+0.00%","Volume":1717,"Open":11.00,"DaysLow":11.00,"DaysHigh":11.40,"LastTradePriceOnly":11.40,"LastTradeTime":"9:57am","LastTradeDate":"2/13/2017","Cap":"SmallCap"},{"Label":"ARISE.ST","Name":"Arise AB","Change":"-0.53%","Volume":16833,"Open":18.80,"DaysLow":18.70,"DaysHigh":19.10,"LastTradePriceOnly":18.70,"LastTradeTime":"10:16am","LastTradeDate":"2/13/2017","Cap":"SmallCap"},{"Label":"AVEG-B.ST","Name":"Avega Group AB ser. B","Change":"-0.79%","Volume":15557,"Open":25.20,"DaysLow":25.00,"DaysHigh":25.20,"LastTradePriceOnly":25.00,"LastTradeTime":"9:47am","LastTradeDate":"2/13/2017","Cap":"SmallCap"},{"Label":"BACTI-B.ST","Name":"Bactiguard Holding AB","Change":"-3.47%","Volume":31451,"Open":16.50,"DaysLow":16.50,"DaysHigh":16.90,"LastTradePriceOnly":16.70,"LastTradeTime":"10:16am","LastTradeDate":"2/13/2017","Cap":"SmallCap"},{"Label":"BEGR.ST","Name":"BE Group AB","Change":"-1.78%","Volume":6080,"Open":45.30,"DaysLow":44.00,"DaysHigh":45.70,"LastTradePriceOnly":44.10,"LastTradeTime":"10:09am","LastTradeDate":"2/13/2017","Cap":"SmallCap"},{"Label":"BELE.ST","Name":"Beijer Electronics AB","Change":"+0.00%","Volume":2523,"Open":38.50,"DaysLow":38.50,"DaysHigh":38.60,"LastTradePriceOnly":38.50,"LastTradeTime":"10:07am","LastTradeDate":"2/13/2017","Cap":"SmallCap"},{"Label":"BRG-B.ST","Name":"Bergs Timber AB ser. B","Change":"+0.90%","Volume":4139,"Open":2.23,"DaysLow":2.21,"DaysHigh":2.23,"LastTradePriceOnly":2.23,"LastTradeTime":"9:14am","LastTradeDate":"2/13/2017","Cap":"SmallCap"},{"Label":"BINV.ST","Name":"BioInvent International AB","Change":"+2.44%","Volume":460790,"Open":2.87,"DaysLow":2.87,"DaysHigh":2.95,"LastTradePriceOnly":2.94,"LastTradeTime":"10:17am","LastTradeDate":"2/13/2017","Cap":"SmallCap"},{"Label":"BIOT.ST","Name":"Biotage AB","Change":"+1.37%","Volume":42688,"Open":43.60,"DaysLow":43.60,"DaysHigh":44.70,"LastTradePriceOnly":44.50,"LastTradeTime":"10:18am","LastTradeDate":"2/13/2017","Cap":"SmallCap"},{"Label":"BORG.ST","Name":"Bjrn Borg AB","Change":"+0.61%","Volume":37241,"Open":33.00,"DaysLow":32.90,"DaysHigh":33.30,"LastTradePriceOnly":33.20,"LastTradeTime":"10:11am","LastTradeDate":"2/13/2017","Cap":"SmallCap"},{"Label":"BEF-SDB.ST","Name":"Black Earth Farming Ltd. SDB","Change":"+0.00%","Volume":0,"Open":6.70,"DaysLow":6.70,"DaysHigh":6.70,"LastTradePriceOnly":6.70,"LastTradeTime":"5:29pm","LastTradeDate":"2/10/2017","Cap":"SmallCap"},{"Label":"BONG.ST","Name":"Bong AB","Change":"+0.00%","Volume":28554,"Open":0.81,"DaysLow":0.80,"DaysHigh":0.81,"LastTradePriceOnly":0.80,"LastTradeTime":"10:11am","LastTradeDate":"2/13/2017","Cap":"SmallCap"},{"Label":"BOUL.ST","Name":"Boule Diagnostics AB","Change":"+2.12%","Volume":2550,"Open":283.00,"DaysLow":280.00,"DaysHigh":289.00,"LastTradePriceOnly":289.00,"LastTradeTime":"10:07am","LastTradeDate":"2/13/2017","Cap":"SmallCap"},{"Label":"BTS-B.ST","Name":"BTS Group AB ser. B","Change":"+0.34%","Volume":1222,"Open":73.50,"DaysLow":73.50,"DaysHigh":74.00,"LastTradePriceOnly":73.75,"LastTradeTime":"9:50am","LastTradeDate":"2/13/2017","Cap":"SmallCap"},{"Label":"CRAD-B.ST","Name":"C-RAD AB ser. B","Change":"+0.77%","Volume":91469,"Open":13.15,"DaysLow":12.80,"DaysHigh":13.40,"LastTradePriceOnly":13.15,"LastTradeTime":"9:46am","LastTradeDate":"2/13/2017","Cap":"SmallCap"},{"Label":"CEVI.ST","Name":"CellaVision AB","Change":"+6.06%","Volume":80672,"Open":120.00,"DaysLow":120.00,"DaysHigh":124.25,"LastTradePriceOnly":122.50,"LastTradeTime":"10:18am","LastTradeDate":"2/13/2017","Cap":"SmallCap"},{"Label":"CCOR-B.ST","Name":"Concordia Maritime AB ser. B","Change":"+0.00%","Volume":13002,"Open":13.80,"DaysLow":13.80,"DaysHigh":13.90,"LastTradePriceOnly":13.80,"LastTradeTime":"10:10am","LastTradeDate":"2/13/2017","Cap":"SmallCap"},{"Label":"CONS-B.ST","Name":"Consilium AB ser. B","Change":"+1.66%","Volume":2298,"Open":106.00,"DaysLow":106.00,"DaysHigh":108.00,"LastTradePriceOnly":107.25,"LastTradeTime":"10:09am","LastTradeDate":"2/13/2017","Cap":"SmallCap"},{"Label":"CTT.ST","Name":"CTT Systems AB","Change":"+0.90%","Volume":11444,"Open":139.00,"DaysLow":139.00,"DaysHigh":143.00,"LastTradePriceOnly":140.25,"LastTradeTime":"10:08am","LastTradeDate":"2/13/2017","Cap":"SmallCap"},{"Label":"DEDI.ST","Name":"Dedicare AB ser. B","Change":"+9.17%","Volume":24032,"Open":115.00,"DaysLow":115.00,"DaysHigh":125.00,"LastTradePriceOnly":125.00,"LastTradeTime":"10:17am","LastTradeDate":"2/13/2017","Cap":"SmallCap"},{"Label":"DGC.ST","Name":"DGC One AB","Change":"+0.00%","Volume":12,"Open":139.50,"DaysLow":139.50,"DaysHigh":139.50,"LastTradePriceOnly":139.50,"LastTradeTime":"9:00am","LastTradeDate":"2/13/2017","Cap":"SmallCap"},{"Label":"DORO.ST","Name":"DORO AB","Change":"+0.00%","Volume":9443,"Open":51.25,"DaysLow":51.25,"DaysHigh":51.75,"LastTradePriceOnly":51.25,"LastTradeTime":"10:17am","LastTradeDate":"2/13/2017","Cap":"SmallCap"},{"Label":"DURC-B.ST","Name":"Duroc AB ser. B","Change":"+3.04%","Volume":3220,"Open":23.00,"DaysLow":23.00,"DaysHigh":23.70,"LastTradePriceOnly":23.70,"LastTradeTime":"9:44am","LastTradeDate":"2/13/2017","Cap":"SmallCap"},{"Label":"ELAN-B.ST","Name":"Elanders AB ser. B","Change":"-0.48%","Volume":6896,"Open":104.50,"DaysLow":103.25,"DaysHigh":104.50,"LastTradePriceOnly":104.00,"LastTradeTime":"10:15am","LastTradeDate":"2/13/2017","Cap":"SmallCap"},{"Label":"ELEC.ST","Name":"Electra Gruppen AB","Change":"+0.36%","Volume":1510,"Open":68.75,"DaysLow":68.75,"DaysHigh":69.00,"LastTradePriceOnly":69.00,"LastTradeTime":"10:14am","LastTradeDate":"2/13/2017","Cap":"SmallCap"},{"Label":"ELOS-B.ST","Name":"Elos Medtech AB ser. B","Change":"+0.00%","Volume":517,"Open":100.50,"DaysLow":100.50,"DaysHigh":100.50,"LastTradePriceOnly":100.50,"LastTradeTime":"9:06am","LastTradeDate":"2/13/2017","Cap":"SmallCap"},{"Label":"ENDO.ST","Name":"Endomines AB","Change":"+0.00%","Volume":100,"Open":19.20,"DaysLow":19.20,"DaysHigh":19.20,"LastTradePriceOnly":19.20,"LastTradeTime":"9:30am","LastTradeDate":"2/13/2017","Cap":"SmallCap"},{"Label":"ENEA.ST","Name":"Enea AB","Change":"-1.28%","Volume":5353,"Open":96.25,"DaysLow":96.25,"DaysHigh":96.75,"LastTradePriceOnly":96.25,"LastTradeTime":"10:09am","LastTradeDate":"2/13/2017","Cap":"SmallCap"},{"Label":"ENRO.ST","Name":"Eniro AB","Change":"+0.76%","Volume":360460,"Open":0.29,"DaysLow":0.28,"DaysHigh":0.29,"LastTradePriceOnly":0.29,"LastTradeTime":"10:07am","LastTradeDate":"2/13/2017","Cap":"SmallCap"},{"Label":"ENRO-PREF.ST","Name":"Eniro AB pref","Change":"-15.57%","Volume":5878,"Open":120.30,"DaysLow":100.00,"DaysHigh":120.30,"LastTradePriceOnly":103.00,"LastTradeTime":"10:16am","LastTradeDate":"2/13/2017","Cap":"SmallCap"},{"Label":"EOLU-B.ST","Name":"Eolus Vind AB ser. B","Change":"+0.00%","Volume":12048,"Open":22.00,"DaysLow":21.80,"DaysHigh":22.00,"LastTradePriceOnly":22.00,"LastTradeTime":"10:16am","LastTradeDate":"2/13/2017","Cap":"SmallCap"},{"Label":"EPIS-B.ST","Name":"Episurf Medical AB B","Change":"+2.24%","Volume":3696,"Open":13.70,"DaysLow":13.50,"DaysHigh":13.70,"LastTradePriceOnly":13.70,"LastTradeTime":"10:17am","LastTradeDate":"2/13/2017","Cap":"SmallCap"},{"Label":"ETX.ST","Name":"Etrion Corporation","Change":"+2.31%","Volume":42038,"Open":2.20,"DaysLow":2.19,"DaysHigh":2.22,"LastTradePriceOnly":2.21,"LastTradeTime":"10:02am","LastTradeDate":"2/13/2017","Cap":"SmallCap"},{"Label":"EWRK.ST","Name":"eWork Group AB","Change":"+0.29%","Volume":2064,"Open":85.25,"DaysLow":85.25,"DaysHigh":85.50,"LastTradePriceOnly":85.50,"LastTradeTime":"10:08am","LastTradeDate":"2/13/2017","Cap":"SmallCap"},{"Label":"FEEL.ST","Name":"Feelgood Svenska AB","Change":"+0.00%","Volume":23456,"Open":2.80,"DaysLow":2.77,"DaysHigh":2.80,"LastTradePriceOnly":2.80,"LastTradeTime":"10:02am","LastTradeDate":"2/13/2017","Cap":"SmallCap"},{"Label":"FPIP.ST","Name":"FormPipe Software AB","Change":"+5.56%","Volume":50018,"Open":12.70,"DaysLow":12.70,"DaysHigh":13.50,"LastTradePriceOnly":13.30,"LastTradeTime":"10:18am","LastTradeDate":"2/13/2017","Cap":"SmallCap"},{"Label":"G5EN.ST","Name":"G5 Entertainment AB","Change":"+0.55%","Volume":8137,"Open":182.50,"DaysLow":182.00,"DaysHigh":184.00,"LastTradePriceOnly":183.50,"LastTradeTime":"10:17am","LastTradeDate":"2/13/2017","Cap":"SmallCap"},{"Label":"GARO.ST","Name":"Garo AB","Change":"+0.00%","Volume":1106,"Open":190.00,"DaysLow":188.00,"DaysHigh":190.50,"LastTradePriceOnly":190.50,"LastTradeTime":"10:01am","LastTradeDate":"2/13/2017","Cap":"SmallCap"},{"Label":"GHP.ST","Name":"GHP Specialty Care AB","Change":"+0.92%","Volume":17797,"Open":11.00,"DaysLow":10.95,"DaysHigh":11.05,"LastTradePriceOnly":10.95,"LastTradeTime":"10:03am","LastTradeDate":"2/13/2017","Cap":"SmallCap"},{"Label":"HMED.ST","Name":"Hansa Medical AB","Change":"+0.00%","Volume":9053,"Open":112.25,"DaysLow":111.75,"DaysHigh":112.75,"LastTradePriceOnly":112.50,"LastTradeTime":"10:15am","LastTradeDate":"2/13/2017","Cap":"SmallCap"},{"Label":"HAV-B.ST","Name":"Havsfrun Investment AB ser. B","Change":"+1.50%","Volume":14,"Open":20.30,"DaysLow":20.30,"DaysHigh":20.30,"LastTradePriceOnly":20.30,"LastTradeTime":"9:42am","LastTradeDate":"2/13/2017","Cap":"SmallCap"},{"Label":"HTRO.ST","Name":"Hexatronic Group AB","Change":"-1.51%","Volume":33621,"Open":40.00,"DaysLow":38.70,"DaysHigh":40.00,"LastTradePriceOnly":39.20,"LastTradeTime":"10:13am","LastTradeDate":"2/13/2017","Cap":"SmallCap"},{"Label":"IAR-B.ST","Name":"I.A.R Systems Group AB ser. B","Change":"+5.09%","Volume":14252,"Open":200.00,"DaysLow":200.00,"DaysHigh":210.00,"LastTradePriceOnly":206.50,"LastTradeTime":"10:10am","LastTradeDate":"2/13/2017","Cap":"SmallCap"},{"Label":"IS.ST","Name":"Image Systems AB","Change":"-2.66%","Volume":6295,"Open":1.88,"DaysLow":1.82,"DaysHigh":1.88,"LastTradePriceOnly":1.83,"LastTradeTime":"10:10am","LastTradeDate":"2/13/2017","Cap":"SmallCap"},{"Label":"ICTA-B.ST","Name":"Intellecta AB ser. B","Change":"+0.97%","Volume":2713,"Open":31.30,"DaysLow":31.30,"DaysHigh":31.30,"LastTradePriceOnly":31.30,"LastTradeTime":"10:12am","LastTradeDate":"2/13/2017","Cap":"SmallCap"},{"Label":"KABE-B.ST","Name":"KABE AB ser. B","Change":"+0.71%","Volume":512,"Open":212.00,"DaysLow":212.00,"DaysHigh":213.50,"LastTradePriceOnly":212.50,"LastTradeTime":"10:10am","LastTradeDate":"2/13/2017","Cap":"SmallCap"},{"Label":"KARO.ST","Name":"Karo Pharma AB","Change":"-0.40%","Volume":46840,"Open":24.90,"DaysLow":24.70,"DaysHigh":25.30,"LastTradePriceOnly":24.70,"LastTradeTime":"10:17am","LastTradeDate":"2/13/2017","Cap":"SmallCap"},{"Label":"KDEV.ST","Name":"Karolinska Development AB ser.B","Change":"+0.00%","Volume":149,"Open":5.95,"DaysLow":5.95,"DaysHigh":5.95,"LastTradePriceOnly":5.95,"LastTradeTime":"9:00am","LastTradeDate":"2/13/2017","Cap":"SmallCap"},{"Label":"KNOW.ST","Name":"Knowit AB","Change":"+0.93%","Volume":31647,"Open":106.00,"DaysLow":106.00,"DaysHigh":111.50,"LastTradePriceOnly":109.00,"LastTradeTime":"10:17am","LastTradeDate":"2/13/2017","Cap":"SmallCap"},{"Label":"LAMM-B.ST","Name":"Lammhults Design Group AB ser. ","Change":"-1.04%","Volume":2176,"Open":72.75,"DaysLow":71.50,"DaysHigh":72.75,"LastTradePriceOnly":71.50,"LastTradeTime":"9:58am","LastTradeDate":"2/13/2017","Cap":"SmallCap"},{"Label":"MEAB-B.ST","Name":"Malmbergs Elektriska AB ser. B","Change":"+1.94%","Volume":150,"Open":158.00,"DaysLow":158.00,"DaysHigh":158.00,"LastTradePriceOnly":158.00,"LastTradeTime":"9:00am","LastTradeDate":"2/13/2017","Cap":"SmallCap"},{"Label":"MCAP.ST","Name":"MedCap AB","Change":"+0.00%","Volume":0,"Open":36.10,"DaysLow":36.10,"DaysHigh":36.10,"LastTradePriceOnly":36.10,"LastTradeTime":"5:29pm","LastTradeDate":"2/10/2017","Cap":"SmallCap"},{"Label":"MSAB-B.ST","Name":"Micro Systemation AB B","Change":"-1.19%","Volume":5742,"Open":63.25,"DaysLow":61.50,"DaysHigh":63.25,"LastTradePriceOnly":62.50,"LastTradeTime":"10:08am","LastTradeDate":"2/13/2017","Cap":"SmallCap"},{"Label":"MSON-A.ST","Name":"Midsona AB ser. A","Change":"+0.00%","Volume":21,"Open":73.50,"DaysLow":73.50,"DaysHigh":73.50,"LastTradePriceOnly":73.50,"LastTradeTime":"9:00am","LastTradeDate":"2/13/2017","Cap":"SmallCap"},{"Label":"MSON-B.ST","Name":"Midsona AB ser. B","Change":"+1.70%","Volume":20793,"Open":49.00,"DaysLow":48.20,"DaysHigh":51.00,"LastTradePriceOnly":50.75,"LastTradeTime":"10:17am","LastTradeDate":"2/13/2017","Cap":"SmallCap"},{"Label":"MIDW-A.ST","Name":"Midway Holding AB ser. A","Change":"+0.00%","Volume":10,"Open":20.00,"DaysLow":20.00,"DaysHigh":20.00,"LastTradePriceOnly":20.00,"LastTradeTime":"9:56am","LastTradeDate":"2/13/2017","Cap":"SmallCap"},{"Label":"MIDW-B.ST","Name":"Midway Holding AB ser. B","Change":"+1.99%","Volume":1239,"Open":20.00,"DaysLow":20.00,"DaysHigh":20.80,"LastTradePriceOnly":20.50,"LastTradeTime":"10:11am","LastTradeDate":"2/13/2017","Cap":"SmallCap"},{"Label":"MOB.ST","Name":"Moberg Pharma AB","Change":"+1.43%","Volume":24350,"Open":70.75,"DaysLow":70.00,"DaysHigh":71.25,"LastTradePriceOnly":71.00,"LastTradeTime":"10:16am","LastTradeDate":"2/13/2017","Cap":"SmallCap"},{"Label":"MQ.ST","Name":"MQ Holding AB","Change":"-2.35%","Volume":116082,"Open":33.90,"DaysLow":33.20,"DaysHigh":33.90,"LastTradePriceOnly":33.30,"LastTradeTime":"10:18am","LastTradeDate":"2/13/2017","Cap":"SmallCap"},{"Label":"MSC-B.ST","Name":"MSC Group AB ser. B","Change":"+0.00%","Volume":6265,"Open":2.23,"DaysLow":2.23,"DaysHigh":2.25,"LastTradePriceOnly":2.23,"LastTradeTime":"10:16am","LastTradeDate":"2/13/2017","Cap":"SmallCap"},{"Label":"MULQ.ST","Name":"MultiQ International AB","Change":"+2.22%","Volume":249010,"Open":0.68,"DaysLow":0.68,"DaysHigh":0.69,"LastTradePriceOnly":0.69,"LastTradeTime":"10:03am","LastTradeDate":"2/13/2017","Cap":"SmallCap"},{"Label":"NAXS.ST","Name":"NAXS AB","Change":"+2.67%","Volume":50,"Open":49.90,"DaysLow":49.90,"DaysHigh":49.90,"LastTradePriceOnly":49.90,"LastTradeTime":"9:00am","LastTradeDate":"2/13/2017","Cap":"SmallCap"},{"Label":"NETI-B.ST","Name":"Net Insight AB ser. B","Change":"-1.82%","Volume":254984,"Open":8.25,"DaysLow":8.10,"DaysHigh":8.25,"LastTradePriceOnly":8.10,"LastTradeTime":"10:18am","LastTradeDate":"2/13/2017","Cap":"SmallCap"},{"Label":"NVP.ST","Name":"NeuroVive Pharmaceutical AB","Change":"+5.71%","Volume":137416,"Open":5.35,"DaysLow":5.30,"DaysHigh":5.80,"LastTradePriceOnly":5.55,"LastTradeTime":"10:16am","LastTradeDate":"2/13/2017","Cap":"SmallCap"},{"Label":"NGS.ST","Name":"NGS Group AB","Change":"+0.98%","Volume":2163,"Open":204.00,"DaysLow":203.00,"DaysHigh":207.50,"LastTradePriceOnly":206.00,"LastTradeTime":"10:00am","LastTradeDate":"2/13/2017","Cap":"SmallCap"},{"Label":"NOMI.ST","Name":"Nordic Mines AB","Change":"+1.042%","Volume":789180,"Open":0.384,"DaysLow":0.384,"DaysHigh":0.391,"LastTradePriceOnly":0.388,"LastTradeTime":"10:14am","LastTradeDate":"2/13/2017","Cap":"SmallCap"},{"Label":"NOTE.ST","Name":"NOTE AB","Change":"+0.58%","Volume":25200,"Open":17.10,"DaysLow":17.00,"DaysHigh":17.20,"LastTradePriceOnly":17.20,"LastTradeTime":"10:17am","LastTradeDate":"2/13/2017","Cap":"SmallCap"},{"Label":"NTEK-B.ST","Name":"NOVOTEK AB ser. B","Change":"+1.00%","Volume":4511,"Open":20.20,"DaysLow":20.20,"DaysHigh":20.60,"LastTradePriceOnly":20.30,"LastTradeTime":"10:14am","LastTradeDate":"2/13/2017","Cap":"SmallCap"},{"Label":"ODD.ST","Name":"Odd Molly International AB","Change":"+1.37%","Volume":4241,"Open":54.75,"DaysLow":54.75,"DaysHigh":55.50,"LastTradePriceOnly":55.50,"LastTradeTime":"10:18am","LastTradeDate":"2/13/2017","Cap":"SmallCap"},{"Label":"ORTI-A.ST","Name":"Ortivus AB ser. A","Change":"-5.52%","Volume":1,"Open":4.11,"DaysLow":4.11,"DaysHigh":4.11,"LastTradePriceOnly":4.11,"LastTradeTime":"10:09am","LastTradeDate":"2/13/2017","Cap":"SmallCap"},{"Label":"ORTI-B.ST","Name":"Ortivus AB ser. B","Change":"+2.41%","Volume":107031,"Open":3.40,"DaysLow":3.33,"DaysHigh":3.40,"LastTradePriceOnly":3.40,"LastTradeTime":"10:15am","LastTradeDate":"2/13/2017","Cap":"SmallCap"},{"Label":"OP.ST","Name":"Oscar Properties Holding AB","Change":"+1.07%","Volume":96832,"Open":70.50,"DaysLow":70.50,"DaysHigh":71.50,"LastTradePriceOnly":71.00,"LastTradeTime":"10:16am","LastTradeDate":"2/13/2017","Cap":"SmallCap"},{"Label":"OP-PREF.ST","Name":"Oscar Properties Holding AB PRE","Change":"+0.39%","Volume":40,"Open":254.50,"DaysLow":254.50,"DaysHigh":255.50,"LastTradePriceOnly":255.50,"LastTradeTime":"10:15am","LastTradeDate":"2/13/2017","Cap":"SmallCap"},{"Label":"OP-PREFB.ST","Name":"Oscar Properties Holding AB PRE","Change":"+0.00%","Volume":1139,"Open":504.00,"DaysLow":503.00,"DaysHigh":504.00,"LastTradePriceOnly":504.00,"LastTradeTime":"10:10am","LastTradeDate":"2/13/2017","Cap":"SmallCap"},{"Label":"POOL-B.ST","Name":"Poolia AB ser. B","Change":"+2.79%","Volume":6505,"Open":18.20,"DaysLow":18.10,"DaysHigh":18.90,"LastTradePriceOnly":18.40,"LastTradeTime":"9:44am","LastTradeDate":"2/13/2017","Cap":"SmallCap"},{"Label":"PREC.ST","Name":"Precise Biometrics AB","Change":"+0.75%","Volume":637314,"Open":4.01,"DaysLow":4.01,"DaysHigh":4.06,"LastTradePriceOnly":4.03,"LastTradeTime":"10:17am","LastTradeDate":"2/13/2017","Cap":"SmallCap"},{"Label":"PREV-B.ST","Name":"Prevas AB ser. B","Change":"-0.68%","Volume":350,"Open":14.50,"DaysLow":14.50,"DaysHigh":14.50,"LastTradePriceOnly":14.50,"LastTradeTime":"9:48am","LastTradeDate":"2/13/2017","Cap":"SmallCap"},{"Label":"PRIC-B.ST","Name":"Pricer AB ser. B","Change":"+3.51%","Volume":585359,"Open":11.75,"DaysLow":11.50,"DaysHigh":11.90,"LastTradePriceOnly":11.80,"LastTradeTime":"10:18am","LastTradeDate":"2/13/2017","Cap":"SmallCap"},{"Label":"PACT.ST","Name":"Proact IT Group AB","Change":"+2.87%","Volume":13730,"Open":175.50,"DaysLow":175.50,"DaysHigh":181.00,"LastTradePriceOnly":179.50,"LastTradeTime":"10:15am","LastTradeDate":"2/13/2017","Cap":"SmallCap"},{"Label":"PROB.ST","Name":"Probi AB","Change":"+1.79%","Volume":3172,"Open":504.00,"DaysLow":504.00,"DaysHigh":514.00,"LastTradePriceOnly":513.00,"LastTradeTime":"10:13am","LastTradeDate":"2/13/2017","Cap":"SmallCap"},{"Label":"PROF-B.ST","Name":"ProfilGruppen AB ser. B","Change":"+0.00%","Volume":1885,"Open":86.25,"DaysLow":86.25,"DaysHigh":86.50,"LastTradePriceOnly":86.25,"LastTradeTime":"10:05am","LastTradeDate":"2/13/2017","Cap":"SmallCap"},{"Label":"REJL-B.ST","Name":"Rejlers AB","Change":"-0.69%","Volume":2175,"Open":72.50,"DaysLow":72.00,"DaysHigh":72.50,"LastTradePriceOnly":72.00,"LastTradeTime":"10:02am","LastTradeDate":"2/13/2017","Cap":"SmallCap"},{"Label":"RNBS.ST","Name":"RNB RETAIL AND BRANDS AB","Change":"+0.60%","Volume":33530,"Open":16.80,"DaysLow":16.70,"DaysHigh":17.00,"LastTradePriceOnly":16.90,"LastTradeTime":"10:16am","LastTradeDate":"2/13/2017","Cap":"SmallCap"},{"Label":"RROS.ST","Name":"Rottneros AB","Change":"+0.00%","Volume":55035,"Open":7.40,"DaysLow":7.35,"DaysHigh":7.45,"LastTradePriceOnly":7.40,"LastTradeTime":"10:07am","LastTradeDate":"2/13/2017","Cap":"SmallCap"},{"Label":"SEAM.ST","Name":"Seamless Distribution AB","Change":"+3.33%","Volume":105,"Open":6.20,"DaysLow":6.20,"DaysHigh":6.20,"LastTradePriceOnly":6.20,"LastTradeTime":"9:12am","LastTradeDate":"2/13/2017","Cap":"SmallCap"},{"Label":"SEMC.ST","Name":"Semcon AB","Change":"+0.44%","Volume":40529,"Open":57.25,"DaysLow":55.50,"DaysHigh":57.50,"LastTradePriceOnly":57.25,"LastTradeTime":"10:17am","LastTradeDate":"2/13/2017","Cap":"SmallCap"},{"Label":"SINT.ST","Name":"SinterCast AB","Change":"+0.31%","Volume":768,"Open":79.00,"DaysLow":79.00,"DaysHigh":80.00,"LastTradePriceOnly":80.00,"LastTradeTime":"9:08am","LastTradeDate":"2/13/2017","Cap":"SmallCap"},{"Label":"SOF-B.ST","Name":"Softronic AB ser. B","Change":"+0.00%","Volume":26200,"Open":8.75,"DaysLow":8.65,"DaysHigh":8.90,"LastTradePriceOnly":8.75,"LastTradeTime":"10:12am","LastTradeDate":"2/13/2017","Cap":"SmallCap"},{"Label":"SPOR.ST","Name":"Sportamore AB","Change":"-2.29%","Volume":1349,"Open":87.00,"DaysLow":85.50,"DaysHigh":87.00,"LastTradePriceOnly":85.50,"LastTradeTime":"10:06am","LastTradeDate":"2/13/2017","Cap":"SmallCap"},{"Label":"STWK.ST","Name":"Stockwik Frvaltning AB","Change":"+4.651%","Volume":184410,"Open":0.043,"DaysLow":0.043,"DaysHigh":0.045,"LastTradePriceOnly":0.045,"LastTradeTime":"10:03am","LastTradeDate":"2/13/2017","Cap":"SmallCap"},{"Label":"STRAX.ST","Name":"Strax AB","Change":"+2.86%","Volume":110,"Open":5.35,"DaysLow":5.35,"DaysHigh":5.40,"LastTradePriceOnly":5.40,"LastTradeTime":"9:34am","LastTradeDate":"2/13/2017","Cap":"SmallCap"},{"Label":"SVIK.ST","Name":"Studsvik AB","Change":"+0.41%","Volume":250,"Open":61.00,"DaysLow":61.00,"DaysHigh":61.00,"LastTradePriceOnly":61.00,"LastTradeTime":"10:07am","LastTradeDate":"2/13/2017","Cap":"SmallCap"},{"Label":"SVED-B.ST","Name":"Svedbergs i Dalstorp AB ser. B","Change":"+0.71%","Volume":1094,"Open":42.00,"DaysLow":42.00,"DaysHigh":42.40,"LastTradePriceOnly":42.30,"LastTradeTime":"10:10am","LastTradeDate":"2/13/2017","Cap":"SmallCap"},{"Label":"SVOL-A.ST","Name":"Svolder AB ser. A","Change":"-0.46%","Volume":208,"Open":323.00,"DaysLow":323.00,"DaysHigh":323.00,"LastTradePriceOnly":323.00,"LastTradeTime":"9:05am","LastTradeDate":"2/13/2017","Cap":"SmallCap"},{"Label":"SVOL-B.ST","Name":"Svolder AB ser. B","Change":"-0.49%","Volume":4054,"Open":203.50,"DaysLow":201.50,"DaysHigh":204.00,"LastTradePriceOnly":202.50,"LastTradeTime":"10:10am","LastTradeDate":"2/13/2017","Cap":"SmallCap"},{"Label":"SWOL-B.ST","Name":"Swedol AB ser. B","Change":"+0.40%","Volume":16862,"Open":24.70,"DaysLow":24.50,"DaysHigh":24.80,"LastTradePriceOnly":24.80,"LastTradeTime":"10:17am","LastTradeDate":"2/13/2017","Cap":"SmallCap"},{"Label":"TRAD.ST","Name":"TradeDoubler AB","Change":"-4.00%","Volume":3155,"Open":4.86,"DaysLow":4.80,"DaysHigh":4.86,"LastTradePriceOnly":4.80,"LastTradeTime":"9:49am","LastTradeDate":"2/13/2017","Cap":"SmallCap"},{"Label":"TRENT.ST","Name":"Trention AB","Change":"-0.47%","Volume":18,"Open":53.00,"DaysLow":53.00,"DaysHigh":53.25,"LastTradePriceOnly":53.25,"LastTradeTime":"9:17am","LastTradeDate":"2/13/2017","Cap":"SmallCap"},{"Label":"TAGR.ST","Name":"Trigon Agri A/S","Change":"-0.599%","Volume":672654,"Open":0.166,"DaysLow":0.166,"DaysHigh":0.167,"LastTradePriceOnly":0.166,"LastTradeTime":"10:08am","LastTradeDate":"2/13/2017","Cap":"SmallCap"},{"Label":"UFLX-B.ST","Name":"Uniflex AB ser. B","Change":"+0.98%","Volume":817,"Open":20.40,"DaysLow":20.40,"DaysHigh":20.70,"LastTradePriceOnly":20.60,"LastTradeTime":"10:09am","LastTradeDate":"2/13/2017","Cap":"SmallCap"},{"Label":"VRG-B.ST","Name":"Venue Retail Group AB ser. B","Change":"+1.54%","Volume":19736,"Open":2.01,"DaysLow":1.97,"DaysHigh":2.01,"LastTradePriceOnly":1.98,"LastTradeTime":"10:17am","LastTradeDate":"2/13/2017","Cap":"SmallCap"},{"Label":"VSSAB-B.ST","Name":"Viking Supply Ships AB ser. B","Change":"+0.00%","Volume":156179,"Open":1.13,"DaysLow":1.10,"DaysHigh":1.13,"LastTradePriceOnly":1.10,"LastTradeTime":"10:15am","LastTradeDate":"2/13/2017","Cap":"SmallCap"},{"Label":"VIT-B.ST","Name":"Vitec Software Group AB ser. B","Change":"-1.33%","Volume":3156,"Open":75.00,"DaysLow":74.00,"DaysHigh":75.00,"LastTradePriceOnly":74.00,"LastTradeTime":"10:18am","LastTradeDate":"2/13/2017","Cap":"SmallCap"},{"Label":"WISE.ST","Name":"Wise Group AB","Change":"+0.36%","Volume":1885,"Open":70.25,"DaysLow":70.25,"DaysHigh":70.50,"LastTradePriceOnly":70.50,"LastTradeTime":"10:17am","LastTradeDate":"2/13/2017","Cap":"SmallCap"},{"Label":"XANO-B.ST","Name":"XANO Industri AB ser. B","Change":"-0.63%","Volume":27,"Open":236.50,"DaysLow":236.50,"DaysHigh":236.50,"LastTradePriceOnly":236.50,"LastTradeTime":"10:10am","LastTradeDate":"2/13/2017","Cap":"SmallCap"}]