[{"Label":"POOL-B.ST","Name":"Poolia AB ser. B","Change":"+1.25%","Volume":6302,"Open":16.50,"DaysLow":16.10,"DaysHigh":16.50,"LastTradePriceOnly":16.20,"LastTradeTime":"2:07pm","LastTradeDate":"11/28/2016"},{"Label":"PREC.ST","Name":"Precise Biometrics AB","Change":"-0.28%","Volume":918531,"Open":3.60,"DaysLow":3.56,"DaysHigh":3.60,"LastTradePriceOnly":3.60,"LastTradeTime":"2:17pm","LastTradeDate":"11/28/2016"},{"Label":"PREV-B.ST","Name":"Prevas AB ser. B","Change":"+3.73%","Volume":2003,"Open":13.90,"DaysLow":13.90,"DaysHigh":13.90,"LastTradePriceOnly":13.90,"LastTradeTime":"12:43pm","LastTradeDate":"11/28/2016"},{"Label":"PRIC-B.ST","Name":"Pricer AB ser. B","Change":"-1.14%","Volume":116375,"Open":8.65,"DaysLow":8.55,"DaysHigh":8.70,"LastTradePriceOnly":8.65,"LastTradeTime":"2:16pm","LastTradeDate":"11/28/2016"},{"Label":"PACT.ST","Name":"Proact IT Group AB","Change":"+1.30%","Volume":1086,"Open":135.00,"DaysLow":135.00,"DaysHigh":137.75,"LastTradePriceOnly":136.75,"LastTradeTime":"1:52pm","LastTradeDate":"11/28/2016"},{"Label":"PROB.ST","Name":"Probi AB","Change":"-1.78%","Volume":6737,"Open":450.00,"DaysLow":437.00,"DaysHigh":450.00,"LastTradePriceOnly":441.00,"LastTradeTime":"2:15pm","LastTradeDate":"11/28/2016"},{"Label":"PROF-B.ST","Name":"ProfilGruppen AB ser. B","Change":"+0.38%","Volume":2365,"Open":65.00,"DaysLow":63.50,"DaysHigh":66.00,"LastTradePriceOnly":65.75,"LastTradeTime":"2:00pm","LastTradeDate":"11/28/2016"},{"Label":"ORTI-A.ST","Name":"Ortivus AB ser. A","Change":"-5.37%","Volume":109,"Open":3.88,"DaysLow":3.88,"DaysHigh":3.88,"LastTradePriceOnly":3.88,"LastTradeTime":"2:12pm","LastTradeDate":"11/28/2016"},{"Label":"ODD.ST","Name":"Odd Molly International AB","Change":"+0.71%","Volume":1466,"Open":43.00,"DaysLow":42.50,"DaysHigh":43.00,"LastTradePriceOnly":42.80,"LastTradeTime":"2:11pm","LastTradeDate":"11/28/2016"},{"Label":"NTEK-B.ST","Name":"NOVOTEK AB ser. B","Change":"-1.04%","Volume":87,"Open":19.30,"DaysLow":19.10,"DaysHigh":19.30,"LastTradePriceOnly":19.10,"LastTradeTime":"1:45pm","LastTradeDate":"11/28/2016"},{"Label":"NOTE.ST","Name":"NOTE AB","Change":"-3.04%","Volume":687160,"Open":15.00,"DaysLow":14.30,"DaysHigh":15.00,"LastTradePriceOnly":14.35,"LastTradeTime":"2:17pm","LastTradeDate":"11/28/2016"},{"Label":"RAY-B.ST","Name":"RaySearch Laboratories AB ser. ","Change":"-0.54%","Volume":5609,"Open":182.00,"DaysLow":181.50,"DaysHigh":184.50,"LastTradePriceOnly":183.00,"LastTradeTime":"1:13pm","LastTradeDate":"11/28/2016"},{"Label":"VSSAB-B.ST","Name":"Viking Supply Ships AB ser. B","Change":"-5.16%","Volume":38038,"Open":1.46,"DaysLow":1.46,"DaysHigh":1.47,"LastTradePriceOnly":1.47,"LastTradeTime":"12:22pm","LastTradeDate":"11/28/2016"},{"Label":"REJL-B.ST","Name":"Rejlers AB","Change":"-0.96%","Volume":227,"Open":77.50,"DaysLow":77.25,"DaysHigh":77.50,"LastTradePriceOnly":77.25,"LastTradeTime":"1:04pm","LastTradeDate":"11/28/2016"},{"Label":"RNBS.ST","Name":"RNB RETAIL AND BRANDS AB","Change":"+0.00%","Volume":11629,"Open":10.60,"DaysLow":10.60,"DaysHigh":10.75,"LastTradePriceOnly":10.70,"LastTradeTime":"1:46pm","LastTradeDate":"11/28/2016"},{"Label":"RROS.ST","Name":"Rottneros AB","Change":"-1.33%","Volume":155846,"Open":7.50,"DaysLow":7.40,"DaysHigh":7.50,"LastTradePriceOnly":7.40,"LastTradeTime":"1:51pm","LastTradeDate":"11/28/2016"},{"Label":"SEAM.ST","Name":"Seamless Distribution AB","Change":"-2.36%","Volume":5077,"Open":6.35,"DaysLow":6.20,"DaysHigh":6.45,"LastTradePriceOnly":6.20,"LastTradeTime":"1:58pm","LastTradeDate":"11/28/2016"},{"Label":"SEMC.ST","Name":"Semcon AB","Change":"+2.22%","Volume":65363,"Open":46.50,"DaysLow":45.80,"DaysHigh":46.90,"LastTradePriceOnly":46.00,"LastTradeTime":"2:13pm","LastTradeDate":"11/28/2016"},{"Label":"SENS.ST","Name":"Sensys Gatso Group AB","Change":"-6.25%","Volume":4988754,"Open":1.73,"DaysLow":1.65,"DaysHigh":1.76,"LastTradePriceOnly":1.65,"LastTradeTime":"2:16pm","LastTradeDate":"11/28/2016"},{"Label":"SINT.ST","Name":"SinterCast AB","Change":"+2.31%","Volume":16113,"Open":88.75,"DaysLow":87.75,"DaysHigh":89.50,"LastTradePriceOnly":88.50,"LastTradeTime":"1:53pm","LastTradeDate":"11/28/2016"},{"Label":"SOF-B.ST","Name":"Softronic AB ser. B","Change":"-0.64%","Volume":12621,"Open":7.80,"DaysLow":7.70,"DaysHigh":7.80,"LastTradePriceOnly":7.75,"LastTradeTime":"2:00pm","LastTradeDate":"11/28/2016"},{"Label":"STWK.ST","Name":"Stockwik Frvaltning AB","Change":"-2.174%","Volume":3795855,"Open":0.046,"DaysLow":0.043,"DaysHigh":0.046,"LastTradePriceOnly":0.045,"LastTradeTime":"1:42pm","LastTradeDate":"11/28/2016"},{"Label":"SVIK.ST","Name":"Studsvik AB","Change":"-1.40%","Volume":2888,"Open":53.75,"DaysLow":53.00,"DaysHigh":54.00,"LastTradePriceOnly":53.00,"LastTradeTime":"2:15pm","LastTradeDate":"11/28/2016"},{"Label":"SVED-B.ST","Name":"Svedbergs i Dalstorp AB ser. B","Change":"-1.18%","Volume":2852,"Open":43.00,"DaysLow":42.00,"DaysHigh":43.00,"LastTradePriceOnly":42.00,"LastTradeTime":"12:43pm","LastTradeDate":"11/28/2016"},{"Label":"SVOL-A.ST","Name":"Svolder AB ser. A","Change":"+11.11%","Volume":281,"Open":229.50,"DaysLow":205.00,"DaysHigh":255.00,"LastTradePriceOnly":255.00,"LastTradeTime":"1:03pm","LastTradeDate":"11/28/2016"},{"Label":"SVOL-B.ST","Name":"Svolder AB ser. B","Change":"-0.54%","Volume":6959,"Open":185.00,"DaysLow":182.00,"DaysHigh":185.00,"LastTradePriceOnly":184.00,"LastTradeTime":"2:11pm","LastTradeDate":"11/28/2016"},{"Label":"TRAC-B.ST","Name":"Traction AB ser. B","Change":"+1.77%","Volume":3192,"Open":141.00,"DaysLow":140.50,"DaysHigh":143.50,"LastTradePriceOnly":143.50,"LastTradeTime":"1:50pm","LastTradeDate":"11/28/2016"},{"Label":"TRAD.ST","Name":"TradeDoubler AB","Change":"-1.82%","Volume":3078,"Open":4.86,"DaysLow":4.85,"DaysHigh":4.99,"LastTradePriceOnly":4.85,"LastTradeTime":"11:58am","LastTradeDate":"11/28/2016"},{"Label":"TAGR.ST","Name":"Trigon Agri A/S","Change":"-6.944%","Volume":99594,"Open":0.216,"DaysLow":0.201,"DaysHigh":0.218,"LastTradePriceOnly":0.201,"LastTradeTime":"2:17pm","LastTradeDate":"11/28/2016"},{"Label":"UFLX-B.ST","Name":"Uniflex AB ser. B","Change":"-0.56%","Volume":25285,"Open":18.00,"DaysLow":17.70,"DaysHigh":18.00,"LastTradePriceOnly":17.90,"LastTradeTime":"1:39pm","LastTradeDate":"11/28/2016"},{"Label":"VRG-B.ST","Name":"Venue Retail Group AB ser. B","Change":"+0.58%","Volume":405992,"Open":1.74,"DaysLow":1.67,"DaysHigh":1.75,"LastTradePriceOnly":1.73,"LastTradeTime":"1:53pm","LastTradeDate":"11/28/2016"},{"Label":"VIT-B.ST","Name":"Vitec Software Group AB ser. B","Change":"+5.32%","Volume":42381,"Open":68.00,"DaysLow":68.00,"DaysHigh":70.50,"LastTradePriceOnly":69.25,"LastTradeTime":"2:10pm","LastTradeDate":"11/28/2016"},{"Label":"XANO-B.ST","Name":"XANO Industri AB ser. B","Change":"+2.91%","Volume":705,"Open":209.00,"DaysLow":209.00,"DaysHigh":212.00,"LastTradePriceOnly":212.00,"LastTradeTime":"2:17pm","LastTradeDate":"11/28/2016"},{"Label":"ACAN-B.ST","Name":"Acando AB ser. B","Change":"+0.00%","Volume":35372,"Open":25.00,"DaysLow":24.60,"DaysHigh":25.00,"LastTradePriceOnly":24.80,"LastTradeTime":"2:16pm","LastTradeDate":"11/28/2016"},{"Label":"ANOD-B.ST","Name":"Addnode Group AB ser. B","Change":"+0.00%","Volume":4,"Open":57.50,"DaysLow":57.50,"DaysHigh":58.00,"LastTradePriceOnly":58.00,"LastTradeTime":"11:37am","LastTradeDate":"11/28/2016"},{"Label":"ATRLJ-B.ST","Name":"Atrium Ljungberg AB ser. B","Change":"+0.60%","Volume":4888,"Open":135.80,"DaysLow":134.50,"DaysHigh":135.80,"LastTradePriceOnly":135.00,"LastTradeTime":"2:17pm","LastTradeDate":"11/28/2016"},{"Label":"ATEL-A.ST","Name":"AllTele Allmnna Svenska Telefon","Change":"-3.33%","Volume":5855,"Open":17.50,"DaysLow":17.40,"DaysHigh":18.00,"LastTradePriceOnly":17.40,"LastTradeTime":"2:16pm","LastTradeDate":"11/28/2016"},{"Label":"ANOT.ST","Name":"Anoto Group AB","Change":"-2.959%","Volume":16103810,"Open":0.170,"DaysLow":0.162,"DaysHigh":0.170,"LastTradePriceOnly":0.164,"LastTradeTime":"2:16pm","LastTradeDate":"11/28/2016"},{"Label":"ARP.ST","Name":"Arctic Paper S.A.","Change":"+0.81%","Volume":1564,"Open":12.40,"DaysLow":12.40,"DaysHigh":12.45,"LastTradePriceOnly":12.40,"LastTradeTime":"2:14pm","LastTradeDate":"11/28/2016"},{"Label":"ARISE.ST","Name":"Arise AB","Change":"+0.98%","Volume":17434,"Open":20.40,"DaysLow":20.30,"DaysHigh":20.60,"LastTradePriceOnly":20.60,"LastTradeTime":"2:11pm","LastTradeDate":"11/28/2016"},{"Label":"DOM.ST","Name":"Dometic Group AB","Change":"-0.71%","Volume":675028,"Open":63.75,"DaysLow":63.20,"DaysHigh":63.90,"LastTradePriceOnly":63.30,"LastTradeTime":"2:14pm","LastTradeDate":"11/28/2016"},{"Label":"AVEG-B.ST","Name":"Avega Group AB ser. B","Change":"+0.00%","Volume":6308,"Open":22.60,"DaysLow":22.50,"DaysHigh":22.60,"LastTradePriceOnly":22.50,"LastTradeTime":"2:14pm","LastTradeDate":"11/28/2016"},{"Label":"BEGR.ST","Name":"BE Group AB","Change":"-2.49%","Volume":4381,"Open":40.00,"DaysLow":39.10,"DaysHigh":40.00,"LastTradePriceOnly":39.20,"LastTradeTime":"12:14pm","LastTradeDate":"11/28/2016"},{"Label":"BELE.ST","Name":"Beijer Electronics AB","Change":"+0.00%","Volume":9448,"Open":38.90,"DaysLow":37.50,"DaysHigh":38.90,"LastTradePriceOnly":37.50,"LastTradeTime":"2:15pm","LastTradeDate":"11/28/2016"},{"Label":"BRG-B.ST","Name":"Bergs Timber AB ser. B","Change":"+0.00%","Volume":21595,"Open":2.10,"DaysLow":2.04,"DaysHigh":2.12,"LastTradePriceOnly":2.08,"LastTradeTime":"1:35pm","LastTradeDate":"11/28/2016"},{"Label":"BESQ.ST","Name":"Besqab AB","Change":"-1.23%","Volume":5146,"Open":204.00,"DaysLow":201.00,"DaysHigh":205.00,"LastTradePriceOnly":201.50,"LastTradeTime":"2:14pm","LastTradeDate":"11/28/2016"},{"Label":"BINV.ST","Name":"BioInvent International AB","Change":"+0.00%","Volume":333666,"Open":2.19,"DaysLow":2.18,"DaysHigh":2.22,"LastTradePriceOnly":2.19,"LastTradeTime":"1:37pm","LastTradeDate":"11/28/2016"},{"Label":"BIOT.ST","Name":"Biotage AB","Change":"-1.04%","Volume":24156,"Open":48.20,"DaysLow":47.50,"DaysHigh":48.30,"LastTradePriceOnly":47.50,"LastTradeTime":"2:13pm","LastTradeDate":"11/28/2016"},{"Label":"BORG.ST","Name":"Bjrn Borg AB","Change":"-1.48%","Volume":66361,"Open":33.70,"DaysLow":32.90,"DaysHigh":33.70,"LastTradePriceOnly":33.20,"LastTradeTime":"2:01pm","LastTradeDate":"11/28/2016"},{"Label":"BEF-SDB.ST","Name":"Black Earth Farming Ltd. SDB","Change":"+0.00%","Volume":576059,"Open":5.05,"DaysLow":5.00,"DaysHigh":5.05,"LastTradePriceOnly":5.05,"LastTradeTime":"2:12pm","LastTradeDate":"11/28/2016"},{"Label":"BONG.ST","Name":"Bong AB","Change":"+0.00%","Volume":110793,"Open":0.77,"DaysLow":0.75,"DaysHigh":0.78,"LastTradePriceOnly":0.77,"LastTradeTime":"1:35pm","LastTradeDate":"11/28/2016"},{"Label":"BOUL.ST","Name":"Boule Diagnostics AB","Change":"-3.33%","Volume":3158,"Open":235.00,"DaysLow":230.00,"DaysHigh":235.00,"LastTradePriceOnly":232.00,"LastTradeTime":"2:13pm","LastTradeDate":"11/28/2016"},{"Label":"BTS-B.ST","Name":"BTS Group AB ser. B","Change":"-0.70%","Volume":1204,"Open":70.00,"DaysLow":70.00,"DaysHigh":70.50,"LastTradePriceOnly":70.50,"LastTradeTime":"12:58pm","LastTradeDate":"11/28/2016"},{"Label":"BULTEN.ST","Name":"Bulten AB","Change":"+0.00%","Volume":9059,"Open":88.50,"DaysLow":86.50,"DaysHigh":89.00,"LastTradePriceOnly":89.00,"LastTradeTime":"2:01pm","LastTradeDate":"11/28/2016"},{"Label":"CRAD-B.ST","Name":"C-RAD AB ser. B","Change":"-2.65%","Volume":25696,"Open":13.65,"DaysLow":12.55,"DaysHigh":13.65,"LastTradePriceOnly":12.85,"LastTradeTime":"1:44pm","LastTradeDate":"11/28/2016"},{"Label":"CEVI.ST","Name":"CellaVision AB","Change":"-1.48%","Volume":87236,"Open":84.00,"DaysLow":82.00,"DaysHigh":84.25,"LastTradePriceOnly":83.00,"LastTradeTime":"2:11pm","LastTradeDate":"11/28/2016"},{"Label":"CCOR-B.ST","Name":"Concordia Maritime AB ser. B","Change":"-0.37%","Volume":39890,"Open":13.55,"DaysLow":13.35,"DaysHigh":13.60,"LastTradePriceOnly":13.55,"LastTradeTime":"2:01pm","LastTradeDate":"11/28/2016"},{"Label":"CONS-B.ST","Name":"Consilium AB ser. B","Change":"+0.00%","Volume":3552,"Open":83.50,"DaysLow":83.50,"DaysHigh":85.75,"LastTradePriceOnly":85.75,"LastTradeTime":"10:55am","LastTradeDate":"11/28/2016"},{"Label":"CTT.ST","Name":"CTT Systems AB","Change":"+0.98%","Volume":7371,"Open":104.00,"DaysLow":102.50,"DaysHigh":105.25,"LastTradePriceOnly":103.50,"LastTradeTime":"1:52pm","LastTradeDate":"11/28/2016"},{"Label":"DEDI.ST","Name":"Dedicare AB ser. B","Change":"-0.61%","Volume":4746,"Open":82.25,"DaysLow":79.00,"DaysHigh":82.25,"LastTradePriceOnly":81.75,"LastTradeTime":"2:13pm","LastTradeDate":"11/28/2016"},{"Label":"DGC.ST","Name":"DGC One AB","Change":"-0.58%","Volume":243,"Open":130.50,"DaysLow":129.00,"DaysHigh":130.50,"LastTradePriceOnly":129.00,"LastTradeTime":"1:59pm","LastTradeDate":"11/28/2016"},{"Label":"DORO.ST","Name":"DORO AB","Change":"-0.46%","Volume":24028,"Open":54.50,"DaysLow":53.75,"DaysHigh":54.50,"LastTradePriceOnly":54.25,"LastTradeTime":"2:09pm","LastTradeDate":"11/28/2016"},{"Label":"DURC-B.ST","Name":"Duroc AB ser. B","Change":"-2.96%","Volume":3178,"Open":14.90,"DaysLow":14.75,"DaysHigh":14.90,"LastTradePriceOnly":14.75,"LastTradeTime":"10:35am","LastTradeDate":"11/28/2016"},{"Label":"ELAN-B.ST","Name":"Elanders AB ser. B","Change":"-0.72%","Volume":18453,"Open":103.00,"DaysLow":102.00,"DaysHigh":103.75,"LastTradePriceOnly":103.75,"LastTradeTime":"1:58pm","LastTradeDate":"11/28/2016"},{"Label":"ELEC.ST","Name":"Electra Gruppen AB","Change":"+1.18%","Volume":977,"Open":63.50,"DaysLow":63.50,"DaysHigh":64.50,"LastTradePriceOnly":64.50,"LastTradeTime":"1:50pm","LastTradeDate":"11/28/2016"},{"Label":"ELOS-B.ST","Name":"Elos Medtech AB ser. B","Change":"-2.24%","Volume":820,"Open":100.00,"DaysLow":98.00,"DaysHigh":100.00,"LastTradePriceOnly":98.00,"LastTradeTime":"11:59am","LastTradeDate":"11/28/2016"},{"Label":"ENDO.ST","Name":"Endomines AB","Change":"+0.00%","Volume":4791,"Open":18.00,"DaysLow":17.80,"DaysHigh":18.40,"LastTradePriceOnly":18.00,"LastTradeTime":"1:08pm","LastTradeDate":"11/28/2016"},{"Label":"ENEA.ST","Name":"Enea AB","Change":"-0.56%","Volume":1232,"Open":87.75,"DaysLow":87.75,"DaysHigh":88.50,"LastTradePriceOnly":88.50,"LastTradeTime":"1:55pm","LastTradeDate":"11/28/2016"},{"Label":"EOLU-B.ST","Name":"Eolus Vind AB ser. B","Change":"-0.42%","Volume":19718,"Open":24.00,"DaysLow":23.70,"DaysHigh":24.30,"LastTradePriceOnly":23.90,"LastTradeTime":"2:07pm","LastTradeDate":"11/28/2016"},{"Label":"EPIS-B.ST","Name":"Episurf Medical AB B","Change":"+14.40%","Volume":57342,"Open":12.15,"DaysLow":12.15,"DaysHigh":14.00,"LastTradePriceOnly":13.90,"LastTradeTime":"2:14pm","LastTradeDate":"11/28/2016"},{"Label":"ETX.ST","Name":"Etrion Corporation","Change":"-3.83%","Volume":310426,"Open":2.30,"DaysLow":2.19,"DaysHigh":2.34,"LastTradePriceOnly":2.26,"LastTradeTime":"1:52pm","LastTradeDate":"11/28/2016"},{"Label":"EWRK.ST","Name":"eWork Group AB","Change":"-0.97%","Volume":4352,"Open":76.75,"DaysLow":75.50,"DaysHigh":77.00,"LastTradePriceOnly":76.25,"LastTradeTime":"2:12pm","LastTradeDate":"11/28/2016"},{"Label":"FEEL.ST","Name":"Feelgood Svenska AB","Change":"-0.95%","Volume":17504,"Open":2.07,"DaysLow":2.00,"DaysHigh":2.08,"LastTradePriceOnly":2.08,"LastTradeTime":"1:43pm","LastTradeDate":"11/28/2016"},{"Label":"FPIP.ST","Name":"FormPipe Software AB","Change":"-1.06%","Volume":32489,"Open":9.40,"DaysLow":9.10,"DaysHigh":9.40,"LastTradePriceOnly":9.30,"LastTradeTime":"1:29pm","LastTradeDate":"11/28/2016"},{"Label":"G5EN.ST","Name":"G5 Entertainment AB","Change":"-2.59%","Volume":23895,"Open":86.50,"DaysLow":83.50,"DaysHigh":86.75,"LastTradePriceOnly":84.75,"LastTradeTime":"2:14pm","LastTradeDate":"11/28/2016"},{"Label":"GHP.ST","Name":"GHP Specialty Care AB","Change":"-0.45%","Volume":21386,"Open":11.20,"DaysLow":11.00,"DaysHigh":11.25,"LastTradePriceOnly":11.15,"LastTradeTime":"1:56pm","LastTradeDate":"11/28/2016"},{"Label":"HAV-B.ST","Name":"Havsfrun Investment AB ser. B","Change":"+0.00%","Volume":5644,"Open":19.20,"DaysLow":19.00,"DaysHigh":19.20,"LastTradePriceOnly":19.20,"LastTradeTime":"1:49pm","LastTradeDate":"11/28/2016"},{"Label":"PNDX-B.ST","Name":"Pandox AB ser. B","Change":"+0.71%","Volume":20473,"Open":139.80,"DaysLow":139.20,"DaysHigh":141.50,"LastTradePriceOnly":140.90,"LastTradeTime":"2:16pm","LastTradeDate":"11/28/2016"},{"Label":"IAR-B.ST","Name":"I.A.R Systems Group AB ser. B","Change":"-1.01%","Volume":835,"Open":197.50,"DaysLow":193.00,"DaysHigh":199.50,"LastTradePriceOnly":195.50,"LastTradeTime":"2:04pm","LastTradeDate":"11/28/2016"},{"Label":"IS.ST","Name":"Image Systems AB","Change":"-3.29%","Volume":55690,"Open":2.43,"DaysLow":2.34,"DaysHigh":2.43,"LastTradePriceOnly":2.35,"LastTradeTime":"2:09pm","LastTradeDate":"11/28/2016"},{"Label":"ICTA-B.ST","Name":"Intellecta AB ser. B","Change":"-2.22%","Volume":92,"Open":27.00,"DaysLow":26.40,"DaysHigh":27.00,"LastTradePriceOnly":26.40,"LastTradeTime":"1:44pm","LastTradeDate":"11/28/2016"},{"Label":"KABE-B.ST","Name":"KABE AB ser. B","Change":"-0.27%","Volume":402,"Open":183.00,"DaysLow":182.00,"DaysHigh":183.00,"LastTradePriceOnly":182.50,"LastTradeTime":"2:02pm","LastTradeDate":"11/28/2016"},{"Label":"KARO.ST","Name":"Karo Pharma AB","Change":"+0.32%","Volume":72021,"Open":31.50,"DaysLow":30.70,"DaysHigh":31.50,"LastTradePriceOnly":31.40,"LastTradeTime":"2:14pm","LastTradeDate":"11/28/2016"},{"Label":"KDEV.ST","Name":"Karolinska Development AB ser.B","Change":"+0.81%","Volume":4490,"Open":6.20,"DaysLow":6.20,"DaysHigh":6.25,"LastTradePriceOnly":6.25,"LastTradeTime":"2:04pm","LastTradeDate":"11/28/2016"},{"Label":"KNOW.ST","Name":"Knowit AB","Change":"+0.00%","Volume":2243,"Open":83.00,"DaysLow":82.25,"DaysHigh":83.50,"LastTradePriceOnly":83.00,"LastTradeTime":"2:03pm","LastTradeDate":"11/28/2016"},{"Label":"LAMM-B.ST","Name":"Lammhults Design Group AB ser. ","Change":"-0.45%","Volume":177,"Open":56.00,"DaysLow":55.75,"DaysHigh":56.00,"LastTradePriceOnly":55.75,"LastTradeTime":"11:26am","LastTradeDate":"11/28/2016"},{"Label":"MEAB-B.ST","Name":"Malmbergs Elektriska AB ser. B","Change":"+1.52%","Volume":210,"Open":147.75,"DaysLow":147.75,"DaysHigh":150.50,"LastTradePriceOnly":150.00,"LastTradeTime":"1:04pm","LastTradeDate":"11/28/2016"},{"Label":"MSAB-B.ST","Name":"Micro Systemation AB B","Change":"+0.00%","Volume":4452,"Open":66.50,"DaysLow":66.25,"DaysHigh":67.25,"LastTradePriceOnly":66.50,"LastTradeTime":"2:13pm","LastTradeDate":"11/28/2016"},{"Label":"MSON-A.ST","Name":"Midsona AB ser. A","Change":"-11.95%","Volume":762,"Open":79.50,"DaysLow":65.50,"DaysHigh":79.50,"LastTradePriceOnly":70.00,"LastTradeTime":"2:01pm","LastTradeDate":"11/28/2016"},{"Label":"MSON-B.ST","Name":"Midsona AB ser. B","Change":"-0.26%","Volume":5889,"Open":38.90,"DaysLow":38.80,"DaysHigh":39.40,"LastTradePriceOnly":39.00,"LastTradeTime":"1:22pm","LastTradeDate":"11/28/2016"},{"Label":"MIDW-B.ST","Name":"Midway Holding AB ser. B","Change":"-1.08%","Volume":3000,"Open":18.40,"DaysLow":18.40,"DaysHigh":18.40,"LastTradePriceOnly":18.40,"LastTradeTime":"10:16am","LastTradeDate":"11/28/2016"},{"Label":"MOB.ST","Name":"Moberg Pharma AB","Change":"+3.18%","Volume":32683,"Open":55.25,"DaysLow":55.25,"DaysHigh":56.75,"LastTradePriceOnly":56.75,"LastTradeTime":"2:11pm","LastTradeDate":"11/28/2016"},{"Label":"MQ.ST","Name":"MQ Holding AB","Change":"-0.27%","Volume":34343,"Open":36.50,"DaysLow":36.00,"DaysHigh":36.50,"LastTradePriceOnly":36.30,"LastTradeTime":"2:04pm","LastTradeDate":"11/28/2016"},{"Label":"MSC-B.ST","Name":"MSC Group AB ser. B","Change":"+0.87%","Volume":5,"Open":2.32,"DaysLow":2.32,"DaysHigh":2.32,"LastTradePriceOnly":2.32,"LastTradeTime":"11:26am","LastTradeDate":"11/28/2016"},{"Label":"MULQ.ST","Name":"MultiQ International AB","Change":"-0.61%","Volume":1010,"Open":0.81,"DaysLow":0.81,"DaysHigh":0.81,"LastTradePriceOnly":0.81,"LastTradeTime":"12:49pm","LastTradeDate":"11/28/2016"},{"Label":"NAXS.ST","Name":"NAXS AB","Change":"+0.41%","Volume":35,"Open":48.80,"DaysLow":48.80,"DaysHigh":49.00,"LastTradePriceOnly":49.00,"LastTradeTime":"11:51am","LastTradeDate":"11/28/2016"},{"Label":"NETI-B.ST","Name":"Net Insight AB ser. B","Change":"-2.00%","Volume":1404255,"Open":7.40,"DaysLow":7.35,"DaysHigh":7.70,"LastTradePriceOnly":7.35,"LastTradeTime":"2:14pm","LastTradeDate":"11/28/2016"},{"Label":"NVP.ST","Name":"NeuroVive Pharmaceutical AB","Change":"-0.88%","Volume":112602,"Open":3.40,"DaysLow":3.26,"DaysHigh":3.42,"LastTradePriceOnly":3.36,"LastTradeTime":"2:14pm","LastTradeDate":"11/28/2016"},{"Label":"NOMI.ST","Name":"Nordic Mines AB","Change":"-0.93%","Volume":1953187,"Open":0.54,"DaysLow":0.51,"DaysHigh":0.54,"LastTradePriceOnly":0.53,"LastTradeTime":"2:13pm","LastTradeDate":"11/28/2016"},{"Label":"AAK.ST","Name":"AAK AB","Change":"-0.18%","Volume":22622,"Open":567.00,"DaysLow":562.00,"DaysHigh":569.00,"LastTradePriceOnly":565.50,"LastTradeTime":"2:16pm","LastTradeDate":"11/28/2016"},{"Label":"ABB.ST","Name":"ABB Ltd","Change":"-0.73%","Volume":529794,"Open":190.00,"DaysLow":188.60,"DaysHigh":190.30,"LastTradePriceOnly":189.20,"LastTradeTime":"2:17pm","LastTradeDate":"11/28/2016"},{"Label":"AOI.ST","Name":"Africa Oil Corp.","Change":"+0.70%","Volume":617534,"Open":12.93,"DaysLow":12.80,"DaysHigh":13.03,"LastTradePriceOnly":13.00,"LastTradeTime":"2:17pm","LastTradeDate":"11/28/2016"},{"Label":"ALFA.ST","Name":"Alfa Laval AB","Change":"-1.27%","Volume":445678,"Open":141.80,"DaysLow":139.80,"DaysHigh":141.80,"LastTradePriceOnly":140.20,"LastTradeTime":"2:15pm","LastTradeDate":"11/28/2016"},{"Label":"ASSA-B.ST","Name":"ASSA ABLOY AB ser. B","Change":"-0.65%","Volume":774654,"Open":168.80,"DaysLow":167.00,"DaysHigh":169.20,"LastTradePriceOnly":167.80,"LastTradeTime":"2:16pm","LastTradeDate":"11/28/2016"},{"Label":"AZN.ST","Name":"AstraZeneca PLC","Change":"-1.10%","Volume":352715,"Open":499.30,"DaysLow":491.90,"DaysHigh":499.40,"LastTradePriceOnly":494.50,"LastTradeTime":"2:16pm","LastTradeDate":"11/28/2016"},{"Label":"ATCO-A.ST","Name":"Atlas Copco AB ser. A","Change":"-0.35%","Volume":810977,"Open":284.40,"DaysLow":281.90,"DaysHigh":284.50,"LastTradePriceOnly":284.00,"LastTradeTime":"2:17pm","LastTradeDate":"11/28/2016"},{"Label":"ATCO-B.ST","Name":"Atlas Copco AB ser. B","Change":"-0.16%","Volume":155364,"Open":252.00,"DaysLow":250.10,"DaysHigh":252.60,"LastTradePriceOnly":252.40,"LastTradeTime":"2:16pm","LastTradeDate":"11/28/2016"},{"Label":"WALL-B.ST","Name":"Wallenstam AB ser. B","Change":"-0.74%","Volume":137283,"Open":68.00,"DaysLow":67.10,"DaysHigh":68.05,"LastTradePriceOnly":67.25,"LastTradeTime":"2:14pm","LastTradeDate":"11/28/2016"},{"Label":"ALIV-SDB.ST","Name":"Autoliv Inc. SDB","Change":"+0.85%","Volume":173635,"Open":945.00,"DaysLow":940.50,"DaysHigh":955.50,"LastTradePriceOnly":953.50,"LastTradeTime":"2:17pm","LastTradeDate":"11/28/2016"},{"Label":"AXFO.ST","Name":"Axfood AB","Change":"-0.51%","Volume":139831,"Open":137.00,"DaysLow":135.10,"DaysHigh":137.10,"LastTradePriceOnly":135.50,"LastTradeTime":"2:15pm","LastTradeDate":"11/28/2016"},{"Label":"AXIS.ST","Name":"Axis AB","Change":"+0.59%","Volume":127,"Open":340.00,"DaysLow":340.00,"DaysHigh":342.00,"LastTradePriceOnly":342.00,"LastTradeTime":"11:58am","LastTradeDate":"11/28/2016"},{"Label":"BETS-B.ST","Name":"Betsson AB ser. B","Change":"-0.11%","Volume":308663,"Open":91.00,"DaysLow":89.95,"DaysHigh":93.05,"LastTradePriceOnly":90.90,"LastTradeTime":"2:15pm","LastTradeDate":"11/28/2016"},{"Label":"BILL.ST","Name":"BillerudKorsns AB","Change":"-1.22%","Volume":163825,"Open":156.00,"DaysLow":153.80,"DaysHigh":156.00,"LastTradePriceOnly":154.10,"LastTradeTime":"2:17pm","LastTradeDate":"11/28/2016"},{"Label":"BOL.ST","Name":"Boliden AB","Change":"+3.08%","Volume":1592913,"Open":246.30,"DaysLow":246.00,"DaysHigh":252.30,"LastTradePriceOnly":251.10,"LastTradeTime":"2:17pm","LastTradeDate":"11/28/2016"},{"Label":"CAST.ST","Name":"Castellum AB","Change":"-0.75%","Volume":523986,"Open":120.00,"DaysLow":118.20,"DaysHigh":120.00,"LastTradePriceOnly":118.60,"LastTradeTime":"2:16pm","LastTradeDate":"11/28/2016"},{"Label":"COMH.ST","Name":"Com Hem Holding AB","Change":"-0.61%","Volume":61377,"Open":80.95,"DaysLow":80.40,"DaysHigh":81.15,"LastTradePriceOnly":80.90,"LastTradeTime":"2:02pm","LastTradeDate":"11/28/2016"},{"Label":"ELUX-A.ST","Name":"Electrolux, AB ser. A","Change":"-1.30%","Volume":241,"Open":225.00,"DaysLow":220.00,"DaysHigh":227.40,"LastTradePriceOnly":220.50,"LastTradeTime":"10:52am","LastTradeDate":"11/28/2016"},{"Label":"ELUX-B.ST","Name":"Electrolux, AB ser. B","Change":"+0.00%","Volume":299058,"Open":212.80,"DaysLow":210.90,"DaysHigh":213.70,"LastTradePriceOnly":213.00,"LastTradeTime":"2:16pm","LastTradeDate":"11/28/2016"},{"Label":"EKTA-B.ST","Name":"Elekta AB ser. B","Change":"+0.51%","Volume":612968,"Open":78.75,"DaysLow":78.40,"DaysHigh":79.20,"LastTradePriceOnly":79.15,"LastTradeTime":"2:16pm","LastTradeDate":"11/28/2016"},{"Label":"ENQ.ST","Name":"EnQuest PLC","Change":"-0.25%","Volume":1935663,"Open":3.20,"DaysLow":3.17,"DaysHigh":3.23,"LastTradePriceOnly":3.23,"LastTradeTime":"2:14pm","LastTradeDate":"11/28/2016"},{"Label":"ERIC-A.ST","Name":"Ericsson, Telefonab. L M ser. A","Change":"+0.58%","Volume":23899,"Open":51.75,"DaysLow":51.30,"DaysHigh":52.00,"LastTradePriceOnly":52.00,"LastTradeTime":"2:09pm","LastTradeDate":"11/28/2016"},{"Label":"ERIC-B.ST","Name":"Ericsson, Telefonab. L M ser. B","Change":"-0.88%","Volume":4201719,"Open":47.75,"DaysLow":46.98,"DaysHigh":47.77,"LastTradePriceOnly":47.39,"LastTradeTime":"2:17pm","LastTradeDate":"11/28/2016"},{"Label":"FABG.ST","Name":"Fabege AB","Change":"+0.14%","Volume":116844,"Open":143.30,"DaysLow":142.50,"DaysHigh":143.60,"LastTradePriceOnly":143.50,"LastTradeTime":"2:16pm","LastTradeDate":"11/28/2016"},{"Label":"BALD-B.ST","Name":"Fastighets AB Balder ser. B","Change":"-0.89%","Volume":132022,"Open":190.00,"DaysLow":188.00,"DaysHigh":190.00,"LastTradePriceOnly":189.20,"LastTradeTime":"2:17pm","LastTradeDate":"11/28/2016"},{"Label":"BALD-PREF.ST","Name":"Fastighets AB Balder pref","Change":"-0.12%","Volume":10003,"Open":332.10,"DaysLow":332.00,"DaysHigh":333.00,"LastTradePriceOnly":332.50,"LastTradeTime":"1:53pm","LastTradeDate":"11/28/2016"},{"Label":"GETI-B.ST","Name":"Getinge AB ser. B","Change":"-0.96%","Volume":216978,"Open":146.30,"DaysLow":144.60,"DaysHigh":146.30,"LastTradePriceOnly":145.00,"LastTradeTime":"2:10pm","LastTradeDate":"11/28/2016"},{"Label":"SHB-A.ST","Name":"Svenska Handelsbanken ser. A","Change":"-1.33%","Volume":1130885,"Open":127.60,"DaysLow":125.80,"DaysHigh":127.80,"LastTradePriceOnly":126.50,"LastTradeTime":"2:16pm","LastTradeDate":"11/28/2016"},{"Label":"SHB-B.ST","Name":"Svenska Handelsbanken ser. B","Change":"-0.48%","Volume":23789,"Open":124.50,"DaysLow":123.50,"DaysHigh":124.90,"LastTradePriceOnly":124.30,"LastTradeTime":"2:17pm","LastTradeDate":"11/28/2016"},{"Label":"HM-B.ST","Name":"Hennes & Mauritz AB, H & M ser.","Change":"-0.44%","Volume":871466,"Open":271.30,"DaysLow":269.50,"DaysHigh":271.80,"LastTradePriceOnly":270.50,"LastTradeTime":"2:17pm","LastTradeDate":"11/28/2016"},{"Label":"HEXA-B.ST","Name":"Hexagon AB ser. B","Change":"+0.71%","Volume":390247,"Open":310.90,"DaysLow":308.30,"DaysHigh":314.70,"LastTradePriceOnly":312.80,"LastTradeTime":"2:17pm","LastTradeDate":"11/28/2016"},{"Label":"HPOL-B.ST","Name":"HEXPOL AB ser. B","Change":"-1.57%","Volume":137320,"Open":79.45,"DaysLow":78.10,"DaysHigh":79.45,"LastTradePriceOnly":78.20,"LastTradeTime":"2:15pm","LastTradeDate":"11/28/2016"},{"Label":"HOLM-A.ST","Name":"Holmen AB ser. A","Change":"-0.61%","Volume":113,"Open":313.20,"DaysLow":311.30,"DaysHigh":313.20,"LastTradePriceOnly":311.30,"LastTradeTime":"11:55am","LastTradeDate":"11/28/2016"},{"Label":"HOLM-B.ST","Name":"Holmen AB ser. B","Change":"-0.80%","Volume":30953,"Open":312.00,"DaysLow":308.50,"DaysHigh":312.00,"LastTradePriceOnly":309.30,"LastTradeTime":"2:12pm","LastTradeDate":"11/28/2016"},{"Label":"HUFV-A.ST","Name":"Hufvudstaden AB ser. A","Change":"-0.72%","Volume":239887,"Open":139.60,"DaysLow":137.10,"DaysHigh":139.60,"LastTradePriceOnly":137.60,"LastTradeTime":"2:14pm","LastTradeDate":"11/28/2016"},{"Label":"HUSQ-A.ST","Name":"Husqvarna AB ser. A","Change":"+0.15%","Volume":4312,"Open":68.30,"DaysLow":67.85,"DaysHigh":68.75,"LastTradePriceOnly":67.95,"LastTradeTime":"2:15pm","LastTradeDate":"11/28/2016"},{"Label":"HUSQ-B.ST","Name":"Husqvarna AB ser. B","Change":"+0.15%","Volume":659630,"Open":68.80,"DaysLow":67.80,"DaysHigh":68.85,"LastTradePriceOnly":67.90,"LastTradeTime":"2:17pm","LastTradeDate":"11/28/2016"},{"Label":"ICA.ST","Name":"ICA Gruppen AB","Change":"-1.15%","Volume":124476,"Open":278.60,"DaysLow":275.00,"DaysHigh":278.60,"LastTradePriceOnly":275.40,"LastTradeTime":"2:17pm","LastTradeDate":"11/28/2016"},{"Label":"INDU-A.ST","Name":"Industrivrden, AB ser. A","Change":"-0.29%","Volume":75894,"Open":170.30,"DaysLow":167.80,"DaysHigh":170.30,"LastTradePriceOnly":169.50,"LastTradeTime":"2:17pm","LastTradeDate":"11/28/2016"},{"Label":"INDU-C.ST","Name":"Industrivrden, AB ser. C","Change":"-0.50%","Volume":149766,"Open":161.00,"DaysLow":158.60,"DaysHigh":161.00,"LastTradePriceOnly":160.30,"LastTradeTime":"2:17pm","LastTradeDate":"11/28/2016"},{"Label":"INDT.ST","Name":"Indutrade AB","Change":"-0.23%","Volume":135796,"Open":175.00,"DaysLow":171.70,"DaysHigh":175.40,"LastTradePriceOnly":173.60,"LastTradeTime":"2:14pm","LastTradeDate":"11/28/2016"},{"Label":"IJ.ST","Name":"Intrum Justitia AB","Change":"+0.24%","Volume":121330,"Open":285.40,"DaysLow":285.40,"DaysHigh":288.50,"LastTradePriceOnly":286.80,"LastTradeTime":"2:15pm","LastTradeDate":"11/28/2016"},{"Label":"INVE-A.ST","Name":"Investor AB ser. A","Change":"-0.36%","Volume":39313,"Open":306.40,"DaysLow":303.50,"DaysHigh":307.00,"LastTradePriceOnly":305.80,"LastTradeTime":"2:16pm","LastTradeDate":"11/28/2016"},{"Label":"INVE-B.ST","Name":"Investor AB ser. B","Change":"-0.51%","Volume":417248,"Open":313.00,"DaysLow":309.40,"DaysHigh":313.10,"LastTradePriceOnly":311.60,"LastTradeTime":"2:17pm","LastTradeDate":"11/28/2016"},{"Label":"JM.ST","Name":"JM AB","Change":"+0.08%","Volume":262601,"Open":253.00,"DaysLow":249.10,"DaysHigh":254.00,"LastTradePriceOnly":251.30,"LastTradeTime":"2:16pm","LastTradeDate":"11/28/2016"},{"Label":"KINV-A.ST","Name":"Kinnevik AB ser. A","Change":"+0.50%","Volume":836,"Open":240.80,"DaysLow":239.00,"DaysHigh":243.30,"LastTradePriceOnly":242.00,"LastTradeTime":"1:56pm","LastTradeDate":"11/28/2016"},{"Label":"KINV-B.ST","Name":"Kinnevik AB ser. B","Change":"-0.13%","Volume":178118,"Open":224.50,"DaysLow":222.30,"DaysHigh":224.60,"LastTradePriceOnly":223.80,"LastTradeTime":"2:15pm","LastTradeDate":"11/28/2016"},{"Label":"LATO-B.ST","Name":"Latour, Investmentab. ser. B","Change":"+0.18%","Volume":26791,"Open":335.00,"DaysLow":333.50,"DaysHigh":338.80,"LastTradePriceOnly":336.30,"LastTradeTime":"2:15pm","LastTradeDate":"11/28/2016"},{"Label":"LIFCO-B.ST","Name":"Lifco AB ser.B","Change":"-1.87%","Volume":6714,"Open":235.00,"DaysLow":228.10,"DaysHigh":235.50,"LastTradePriceOnly":231.20,"LastTradeTime":"2:15pm","LastTradeDate":"11/28/2016"},{"Label":"LOOM-B.ST","Name":"Loomis AB ser. B","Change":"-0.16%","Volume":68322,"Open":252.30,"DaysLow":251.50,"DaysHigh":254.00,"LastTradePriceOnly":252.30,"LastTradeTime":"2:16pm","LastTradeDate":"11/28/2016"},{"Label":"LUND-B.ST","Name":"Lundbergfretagen AB, L E ser. B","Change":"+1.26%","Volume":146058,"Open":555.50,"DaysLow":553.50,"DaysHigh":566.50,"LastTradePriceOnly":564.00,"LastTradeTime":"2:15pm","LastTradeDate":"11/28/2016"},{"Label":"LUMI-SDB.ST","Name":"Lundin Mining Corporation SDB","Change":"+0.76%","Volume":527986,"Open":48.02,"DaysLow":47.20,"DaysHigh":48.07,"LastTradePriceOnly":47.51,"LastTradeTime":"2:13pm","LastTradeDate":"11/28/2016"},{"Label":"LUPE.ST","Name":"Lundin Petroleum AB","Change":"-0.59%","Volume":382182,"Open":169.70,"DaysLow":166.90,"DaysHigh":170.00,"LastTradePriceOnly":168.80,"LastTradeTime":"2:16pm","LastTradeDate":"11/28/2016"},{"Label":"MELK.ST","Name":"Melker Schrling AB","Change":"+0.09%","Volume":8522,"Open":537.50,"DaysLow":532.00,"DaysHigh":540.50,"LastTradePriceOnly":539.50,"LastTradeTime":"2:15pm","LastTradeDate":"11/28/2016"},{"Label":"MIC-SDB.ST","Name":"Millicom International Cellular","Change":"-0.88%","Volume":89206,"Open":399.50,"DaysLow":392.70,"DaysHigh":399.50,"LastTradePriceOnly":395.90,"LastTradeTime":"2:16pm","LastTradeDate":"11/28/2016"},{"Label":"MTG-B.ST","Name":"Modern Times Group MTG AB ser. ","Change":"-0.72%","Volume":60733,"Open":235.00,"DaysLow":232.90,"DaysHigh":235.00,"LastTradePriceOnly":234.10,"LastTradeTime":"2:13pm","LastTradeDate":"11/28/2016"},{"Label":"NCC-A.ST","Name":"NCC AB ser. A","Change":"-0.45%","Volume":1528,"Open":222.00,"DaysLow":220.70,"DaysHigh":222.00,"LastTradePriceOnly":221.00,"LastTradeTime":"12:58pm","LastTradeDate":"11/28/2016"},{"Label":"NCC-B.ST","Name":"NCC AB ser. B","Change":"-0.63%","Volume":93464,"Open":222.00,"DaysLow":220.50,"DaysHigh":222.30,"LastTradePriceOnly":220.80,"LastTradeTime":"2:17pm","LastTradeDate":"11/28/2016"},{"Label":"NIBE-B.ST","Name":"NIBE Industrier AB ser. B","Change":"-0.79%","Volume":260435,"Open":69.50,"DaysLow":68.45,"DaysHigh":69.50,"LastTradePriceOnly":68.85,"LastTradeTime":"2:17pm","LastTradeDate":"11/28/2016"},{"Label":"NOBI.ST","Name":"Nobia AB","Change":"-0.84%","Volume":419689,"Open":76.95,"DaysLow":75.55,"DaysHigh":77.35,"LastTradePriceOnly":76.30,"LastTradeTime":"2:17pm","LastTradeDate":"11/28/2016"},{"Label":"NDA-SEK.ST","Name":"Nordea Bank AB","Change":"-1.54%","Volume":3142387,"Open":97.20,"DaysLow":95.70,"DaysHigh":97.40,"LastTradePriceOnly":95.95,"LastTradeTime":"2:17pm","LastTradeDate":"11/28/2016"},{"Label":"WISE.ST","Name":"Wise Group AB","Change":"+0.38%","Volume":9397,"Open":66.75,"DaysLow":63.50,"DaysHigh":67.00,"LastTradePriceOnly":66.75,"LastTradeTime":"2:15pm","LastTradeDate":"11/28/2016"},{"Label":"PEAB-B.ST","Name":"Peab AB ser. B","Change":"-0.83%","Volume":189593,"Open":72.40,"DaysLow":71.35,"DaysHigh":72.55,"LastTradePriceOnly":71.65,"LastTradeTime":"2:14pm","LastTradeDate":"11/28/2016"},{"Label":"RATO-A.ST","Name":"Ratos AB ser. A","Change":"-0.97%","Volume":3063,"Open":56.50,"DaysLow":55.20,"DaysHigh":56.50,"LastTradePriceOnly":56.00,"LastTradeTime":"2:15pm","LastTradeDate":"11/28/2016"},{"Label":"RATO-B.ST","Name":"Ratos AB ser. B","Change":"-0.51%","Volume":502382,"Open":39.30,"DaysLow":38.67,"DaysHigh":39.31,"LastTradePriceOnly":39.00,"LastTradeTime":"2:14pm","LastTradeDate":"11/28/2016"},{"Label":"RATO-PREF.ST","Name":"Ratos AB pref","Change":"-0.22%","Volume":337,"Open":1854.00,"DaysLow":1847.00,"DaysHigh":1854.00,"LastTradePriceOnly":1850.00,"LastTradeTime":"2:16pm","LastTradeDate":"11/28/2016"},{"Label":"SAAB-B.ST","Name":"SAAB AB ser. B","Change":"-0.12%","Volume":112070,"Open":337.60,"DaysLow":333.20,"DaysHigh":337.80,"LastTradePriceOnly":336.40,"LastTradeTime":"2:16pm","LastTradeDate":"11/28/2016"},{"Label":"SAND.ST","Name":"Sandvik AB","Change":"-1.16%","Volume":2335707,"Open":112.40,"DaysLow":111.00,"DaysHigh":112.50,"LastTradePriceOnly":111.10,"LastTradeTime":"2:17pm","LastTradeDate":"11/28/2016"},{"Label":"SCA-A.ST","Name":"Svenska Cellulosa AB SCA ser. A","Change":"-0.61%","Volume":8242,"Open":246.90,"DaysLow":243.20,"DaysHigh":246.90,"LastTradePriceOnly":243.20,"LastTradeTime":"2:16pm","LastTradeDate":"11/28/2016"},{"Label":"SCA-B.ST","Name":"Svenska Cellulosa AB SCA ser. B","Change":"-0.98%","Volume":418875,"Open":245.40,"DaysLow":242.80,"DaysHigh":245.40,"LastTradePriceOnly":243.30,"LastTradeTime":"2:17pm","LastTradeDate":"11/28/2016"},{"Label":"SEB-A.ST","Name":"Skandinaviska Enskilda Banken s","Change":"-0.86%","Volume":2091190,"Open":92.85,"DaysLow":91.40,"DaysHigh":92.85,"LastTradePriceOnly":92.20,"LastTradeTime":"2:17pm","LastTradeDate":"11/28/2016"},{"Label":"SEB-C.ST","Name":"Skandinaviska Enskilda Banken s","Change":"-1.56%","Volume":21239,"Open":93.00,"DaysLow":91.75,"DaysHigh":93.00,"LastTradePriceOnly":91.75,"LastTradeTime":"2:16pm","LastTradeDate":"11/28/2016"},{"Label":"SECU-B.ST","Name":"Securitas AB ser. B","Change":"+0.91%","Volume":303481,"Open":131.90,"DaysLow":131.50,"DaysHigh":133.20,"LastTradePriceOnly":133.00,"LastTradeTime":"2:17pm","LastTradeDate":"11/28/2016"},{"Label":"SKA-B.ST","Name":"Skanska AB ser. B","Change":"-0.05%","Volume":591137,"Open":210.60,"DaysLow":209.30,"DaysHigh":211.20,"LastTradePriceOnly":210.50,"LastTradeTime":"2:17pm","LastTradeDate":"11/28/2016"},{"Label":"SKF-A.ST","Name":"SKF, AB ser. A","Change":"-1.39%","Volume":21736,"Open":165.80,"DaysLow":163.00,"DaysHigh":165.80,"LastTradePriceOnly":163.50,"LastTradeTime":"2:10pm","LastTradeDate":"11/28/2016"},{"Label":"SKF-B.ST","Name":"SKF, AB ser. B","Change":"-1.62%","Volume":1153205,"Open":166.00,"DaysLow":163.10,"DaysHigh":166.00,"LastTradePriceOnly":163.70,"LastTradeTime":"2:17pm","LastTradeDate":"11/28/2016"},{"Label":"SSAB-A.ST","Name":"SSAB AB ser. A","Change":"-1.09%","Volume":1933367,"Open":36.00,"DaysLow":35.23,"DaysHigh":36.31,"LastTradePriceOnly":35.52,"LastTradeTime":"2:15pm","LastTradeDate":"11/28/2016"},{"Label":"SSAB-B.ST","Name":"SSAB AB ser. B","Change":"-0.37%","Volume":2574620,"Open":29.70,"DaysLow":29.21,"DaysHigh":30.15,"LastTradePriceOnly":29.66,"LastTradeTime":"2:14pm","LastTradeDate":"11/28/2016"},{"Label":"STE-A.ST","Name":"Stora Enso Oyj ser. A","Change":"-0.99%","Volume":3730,"Open":97.00,"DaysLow":95.00,"DaysHigh":97.00,"LastTradePriceOnly":95.00,"LastTradeTime":"2:05pm","LastTradeDate":"11/28/2016"},{"Label":"STE-R.ST","Name":"Stora Enso Oyj ser. R","Change":"-1.12%","Volume":237021,"Open":89.60,"DaysLow":88.30,"DaysHigh":89.75,"LastTradePriceOnly":88.50,"LastTradeTime":"2:14pm","LastTradeDate":"11/28/2016"},{"Label":"SWED-A.ST","Name":"Swedbank AB ser A","Change":"-0.56%","Volume":1836839,"Open":214.20,"DaysLow":212.60,"DaysHigh":214.20,"LastTradePriceOnly":213.30,"LastTradeTime":"2:17pm","LastTradeDate":"11/28/2016"},{"Label":"SWMA.ST","Name":"Swedish Match AB","Change":"+0.55%","Volume":198383,"Open":290.10,"DaysLow":287.50,"DaysHigh":292.50,"LastTradePriceOnly":291.70,"LastTradeTime":"2:16pm","LastTradeDate":"11/28/2016"},{"Label":"SOBI.ST","Name":"Swedish Orphan Biovitrum AB","Change":"-0.68%","Volume":336171,"Open":95.90,"DaysLow":94.50,"DaysHigh":96.05,"LastTradePriceOnly":95.30,"LastTradeTime":"2:16pm","LastTradeDate":"11/28/2016"},{"Label":"TEL2-A.ST","Name":"Tele2 AB ser. A","Change":"+7.15%","Volume":2847,"Open":83.95,"DaysLow":83.95,"DaysHigh":90.00,"LastTradePriceOnly":89.95,"LastTradeTime":"1:37pm","LastTradeDate":"11/28/2016"},{"Label":"TEL2-B.ST","Name":"Tele2 AB ser. B","Change":"+0.50%","Volume":924566,"Open":70.55,"DaysLow":70.30,"DaysHigh":71.55,"LastTradePriceOnly":70.85,"LastTradeTime":"2:16pm","LastTradeDate":"11/28/2016"},{"Label":"TIEN.ST","Name":"Tieto Corporation","Change":"-1.08%","Volume":8599,"Open":240.00,"DaysLow":237.00,"DaysHigh":240.00,"LastTradePriceOnly":237.90,"LastTradeTime":"1:54pm","LastTradeDate":"11/28/2016"},{"Label":"TREL-B.ST","Name":"Trelleborg AB ser. B","Change":"-0.76%","Volume":284593,"Open":170.30,"DaysLow":168.20,"DaysHigh":170.30,"LastTradePriceOnly":169.00,"LastTradeTime":"2:15pm","LastTradeDate":"11/28/2016"},{"Label":"VOLV-A.ST","Name":"Volvo, AB ser. A","Change":"-1.21%","Volume":137967,"Open":98.95,"DaysLow":97.65,"DaysHigh":98.95,"LastTradePriceOnly":97.80,"LastTradeTime":"2:16pm","LastTradeDate":"11/28/2016"},{"Label":"VOLV-B.ST","Name":"Volvo, AB ser. B","Change":"-1.41%","Volume":1910510,"Open":99.05,"DaysLow":97.70,"DaysHigh":99.05,"LastTradePriceOnly":97.80,"LastTradeTime":"2:16pm","LastTradeDate":"11/28/2016"},{"Label":"ACTI.ST","Name":"Active Biotech AB","Change":"-0.49%","Volume":40739,"Open":10.20,"DaysLow":9.80,"DaysHigh":10.35,"LastTradePriceOnly":10.10,"LastTradeTime":"2:12pm","LastTradeDate":"11/28/2016"},{"Label":"ADDT-B.ST","Name":"Addtech AB ser. B","Change":"-0.38%","Volume":10369,"Open":132.75,"DaysLow":131.00,"DaysHigh":133.25,"LastTradePriceOnly":132.25,"LastTradeTime":"2:13pm","LastTradeDate":"11/28/2016"},{"Label":"ARCM.ST","Name":"Arcam AB","Change":"+0.00%","Volume":21862,"Open":300.00,"DaysLow":299.50,"DaysHigh":300.50,"LastTradePriceOnly":300.00,"LastTradeTime":"1:53pm","LastTradeDate":"11/28/2016"},{"Label":"AZA.ST","Name":"Avanza Bank Holding AB","Change":"+1.12%","Volume":10709,"Open":356.00,"DaysLow":351.00,"DaysHigh":364.00,"LastTradePriceOnly":360.00,"LastTradeTime":"2:16pm","LastTradeDate":"11/28/2016"},{"Label":"BBTO-B.ST","Name":"B&B TOOLS AB ser. B","Change":"-2.15%","Volume":15257,"Open":186.00,"DaysLow":181.00,"DaysHigh":186.00,"LastTradePriceOnly":182.00,"LastTradeTime":"2:17pm","LastTradeDate":"11/28/2016"},{"Label":"BACTI-B.ST","Name":"Bactiguard Holding AB","Change":"-2.35%","Volume":4463,"Open":17.00,"DaysLow":16.60,"DaysHigh":17.10,"LastTradePriceOnly":16.60,"LastTradeTime":"1:52pm","LastTradeDate":"11/28/2016"},{"Label":"BEIA-B.ST","Name":"Beijer Alma AB ser. B","Change":"+2.33%","Volume":3530,"Open":218.50,"DaysLow":215.00,"DaysHigh":219.50,"LastTradePriceOnly":219.50,"LastTradeTime":"2:16pm","LastTradeDate":"11/28/2016"},{"Label":"BEIJ-B.ST","Name":"Beijer Ref AB ser. B","Change":"+0.00%","Volume":3414,"Open":216.00,"DaysLow":210.50,"DaysHigh":220.00,"LastTradePriceOnly":219.50,"LastTradeTime":"1:42pm","LastTradeDate":"11/28/2016"},{"Label":"BILI-A.ST","Name":"Bilia AB ser. A","Change":"+1.02%","Volume":20144,"Open":199.00,"DaysLow":197.00,"DaysHigh":200.00,"LastTradePriceOnly":198.50,"LastTradeTime":"2:11pm","LastTradeDate":"11/28/2016"},{"Label":"BIOG-B.ST","Name":"BioGaia AB ser. B","Change":"+0.17%","Volume":1929,"Open":289.00,"DaysLow":288.00,"DaysHigh":290.00,"LastTradePriceOnly":290.00,"LastTradeTime":"2:08pm","LastTradeDate":"11/28/2016"},{"Label":"PXXS-SDB.ST","Name":"BlackPearl Resources Inc. SDB","Change":"-3.32%","Volume":485354,"Open":12.00,"DaysLow":11.15,"DaysHigh":12.00,"LastTradePriceOnly":11.65,"LastTradeTime":"2:13pm","LastTradeDate":"11/28/2016"},{"Label":"BUFAB.ST","Name":"Bufab AB","Change":"+0.65%","Volume":37183,"Open":77.75,"DaysLow":77.00,"DaysHigh":77.75,"LastTradePriceOnly":77.25,"LastTradeTime":"2:11pm","LastTradeDate":"11/28/2016"},{"Label":"BURE.ST","Name":"Bure Equity AB","Change":"-1.52%","Volume":65544,"Open":99.00,"DaysLow":96.25,"DaysHigh":99.00,"LastTradePriceOnly":97.50,"LastTradeTime":"2:15pm","LastTradeDate":"11/28/2016"},{"Label":"BMAX.ST","Name":"Byggmax Group AB","Change":"-1.28%","Volume":30022,"Open":58.75,"DaysLow":58.00,"DaysHigh":58.75,"LastTradePriceOnly":58.00,"LastTradeTime":"2:17pm","LastTradeDate":"11/28/2016"},{"Label":"CATE.ST","Name":"Catena AB","Change":"+0.00%","Volume":4863,"Open":126.00,"DaysLow":125.75,"DaysHigh":126.25,"LastTradePriceOnly":126.25,"LastTradeTime":"1:58pm","LastTradeDate":"11/28/2016"},{"Label":"CCC.ST","Name":"Cavotec SA","Change":"+0.83%","Volume":6850,"Open":24.10,"DaysLow":24.10,"DaysHigh":24.50,"LastTradePriceOnly":24.30,"LastTradeTime":"10:23am","LastTradeDate":"11/28/2016"},{"Label":"CLA-B.ST","Name":"Cloetta AB ser. B","Change":"+1.04%","Volume":392573,"Open":29.00,"DaysLow":28.80,"DaysHigh":29.20,"LastTradePriceOnly":29.20,"LastTradeTime":"2:11pm","LastTradeDate":"11/28/2016"},{"Label":"CLAS-B.ST","Name":"Clas Ohlson AB ser. B","Change":"+0.00%","Volume":16989,"Open":129.00,"DaysLow":128.50,"DaysHigh":129.50,"LastTradePriceOnly":129.00,"LastTradeTime":"2:16pm","LastTradeDate":"11/28/2016"},{"Label":"COIC.ST","Name":"Concentric AB","Change":"-0.22%","Volume":2783,"Open":113.00,"DaysLow":111.50,"DaysHigh":113.50,"LastTradePriceOnly":112.75,"LastTradeTime":"1:40pm","LastTradeDate":"11/28/2016"},{"Label":"CORE.ST","Name":"Corem Property Group AB","Change":"-2.23%","Volume":1309,"Open":36.00,"DaysLow":35.00,"DaysHigh":36.10,"LastTradePriceOnly":35.00,"LastTradeTime":"1:29pm","LastTradeDate":"11/28/2016"},{"Label":"CORE-PREF.ST","Name":"Corem Property Group AB Pref","Change":"+0.85%","Volume":7210,"Open":147.00,"DaysLow":147.00,"DaysHigh":148.25,"LastTradePriceOnly":148.25,"LastTradeTime":"2:03pm","LastTradeDate":"11/28/2016"},{"Label":"CRED-A.ST","Name":"Creades AB A","Change":"+1.46%","Volume":2028,"Open":245.00,"DaysLow":240.50,"DaysHigh":245.00,"LastTradePriceOnly":244.00,"LastTradeTime":"1:50pm","LastTradeDate":"11/28/2016"},{"Label":"DIOS.ST","Name":"Dis Fastigheter AB","Change":"+2.11%","Volume":293633,"Open":59.50,"DaysLow":59.25,"DaysHigh":60.50,"LastTradePriceOnly":60.50,"LastTradeTime":"2:16pm","LastTradeDate":"11/28/2016"},{"Label":"DUNI.ST","Name":"Duni AB","Change":"+0.22%","Volume":8918,"Open":117.00,"DaysLow":116.00,"DaysHigh":117.00,"LastTradePriceOnly":116.00,"LastTradeTime":"1:57pm","LastTradeDate":"11/28/2016"},{"Label":"DUST.ST","Name":"Dustin Group AB","Change":"-0.42%","Volume":23019,"Open":59.50,"DaysLow":59.25,"DaysHigh":59.50,"LastTradePriceOnly":59.50,"LastTradeTime":"2:07pm","LastTradeDate":"11/28/2016"},{"Label":"ECEX.ST","Name":"East Capital Explorer AB","Change":"+0.39%","Volume":6113,"Open":63.50,"DaysLow":63.00,"DaysHigh":64.00,"LastTradePriceOnly":63.75,"LastTradeTime":"2:15pm","LastTradeDate":"11/28/2016"},{"Label":"ELTEL.ST","Name":"Eltel AB","Change":"+0.47%","Volume":182035,"Open":53.75,"DaysLow":52.75,"DaysHigh":53.75,"LastTradePriceOnly":53.25,"LastTradeTime":"2:12pm","LastTradeDate":"11/28/2016"},{"Label":"ENRO.ST","Name":"Eniro AB","Change":"+0.7522%","Volume":1631720,"Open":0.2511,"DaysLow":0.2403,"DaysHigh":0.2580,"LastTradePriceOnly":0.2545,"LastTradeTime":"2:08pm","LastTradeDate":"11/28/2016"},{"Label":"ENRO-PREF.ST","Name":"Eniro AB pref","Change":"+0.69%","Volume":4186,"Open":128.10,"DaysLow":128.10,"DaysHigh":130.80,"LastTradePriceOnly":130.50,"LastTradeTime":"2:10pm","LastTradeDate":"11/28/2016"},{"Label":"FAG.ST","Name":"Fagerhult, AB","Change":"-0.47%","Volume":2614,"Open":210.00,"DaysLow":209.00,"DaysHigh":211.00,"LastTradePriceOnly":210.50,"LastTradeTime":"2:01pm","LastTradeDate":"11/28/2016"},{"Label":"FPAR.ST","Name":"Fast Partner AB","Change":"+0.36%","Volume":23226,"Open":139.00,"DaysLow":138.00,"DaysHigh":141.00,"LastTradePriceOnly":139.50,"LastTradeTime":"2:14pm","LastTradeDate":"11/28/2016"},{"Label":"FPAR-PREF.ST","Name":"Fast Partner AB Pref","Change":"+0.00%","Volume":227,"Open":326.00,"DaysLow":325.00,"DaysHigh":327.00,"LastTradePriceOnly":326.00,"LastTradeTime":"1:30pm","LastTradeDate":"11/28/2016"},{"Label":"FOI-B.ST","Name":"Fenix Outdoor International AG ","Change":"-1.96%","Volume":533,"Open":610.00,"DaysLow":599.00,"DaysHigh":610.00,"LastTradePriceOnly":600.00,"LastTradeTime":"2:16pm","LastTradeDate":"11/28/2016"},{"Label":"FING-B.ST","Name":"Fingerprint Cards AB ser. B","Change":"-1.48%","Volume":3315844,"Open":81.05,"DaysLow":79.00,"DaysHigh":81.40,"LastTradePriceOnly":79.80,"LastTradeTime":"2:17pm","LastTradeDate":"11/28/2016"},{"Label":"GRNG.ST","Name":"Grnges AB","Change":"+1.52%","Volume":195564,"Open":82.25,"DaysLow":81.75,"DaysHigh":83.25,"LastTradePriceOnly":83.25,"LastTradeTime":"2:05pm","LastTradeDate":"11/28/2016"},{"Label":"GUNN.ST","Name":"Gunnebo AB","Change":"+0.51%","Volume":10924,"Open":39.60,"DaysLow":39.20,"DaysHigh":39.60,"LastTradePriceOnly":39.40,"LastTradeTime":"2:12pm","LastTradeDate":"11/28/2016"},{"Label":"HLDX.ST","Name":"Haldex AB","Change":"+0.00%","Volume":17134,"Open":116.00,"DaysLow":115.75,"DaysHigh":116.25,"LastTradePriceOnly":116.00,"LastTradeTime":"1:36pm","LastTradeDate":"11/28/2016"},{"Label":"HEBA-B.ST","Name":"Heba Fastighets AB ser. B","Change":"+2.24%","Volume":661,"Open":112.00,"DaysLow":112.00,"DaysHigh":114.00,"LastTradePriceOnly":114.00,"LastTradeTime":"2:11pm","LastTradeDate":"11/28/2016"},{"Label":"HEMF.ST","Name":"Hemfosa Fastigheter AB","Change":"+0.30%","Volume":368540,"Open":83.75,"DaysLow":83.75,"DaysHigh":84.25,"LastTradePriceOnly":84.00,"LastTradeTime":"1:55pm","LastTradeDate":"11/28/2016"},{"Label":"HEMF-PREF.ST","Name":"Hemfosa Fastigheter Pref AB","Change":"+0.00%","Volume":4797,"Open":160.50,"DaysLow":159.00,"DaysHigh":160.50,"LastTradePriceOnly":160.00,"LastTradeTime":"1:53pm","LastTradeDate":"11/28/2016"},{"Label":"HIQ.ST","Name":"HiQ International AB","Change":"-1.24%","Volume":37499,"Open":60.75,"DaysLow":59.50,"DaysHigh":60.75,"LastTradePriceOnly":59.75,"LastTradeTime":"2:09pm","LastTradeDate":"11/28/2016"},{"Label":"HMS.ST","Name":"HMS Networks AB","Change":"-0.18%","Volume":272,"Open":284.00,"DaysLow":279.00,"DaysHigh":284.00,"LastTradePriceOnly":283.50,"LastTradeTime":"9:38am","LastTradeDate":"11/28/2016"},{"Label":"INWI.ST","Name":"Inwido AB","Change":"+0.00%","Volume":174504,"Open":90.00,"DaysLow":88.50,"DaysHigh":90.50,"LastTradePriceOnly":88.75,"LastTradeTime":"2:11pm","LastTradeDate":"11/28/2016"},{"Label":"ITAB-B.ST","Name":"ITAB Shop Concept AB ser. B","Change":"-1.03%","Volume":9565,"Open":71.00,"DaysLow":71.00,"DaysHigh":72.75,"LastTradePriceOnly":72.00,"LastTradeTime":"1:39pm","LastTradeDate":"11/28/2016"},{"Label":"KAHL.ST","Name":"KappAhl AB","Change":"+0.46%","Volume":33730,"Open":43.70,"DaysLow":43.70,"DaysHigh":44.20,"LastTradePriceOnly":43.80,"LastTradeTime":"2:16pm","LastTradeDate":"11/28/2016"},{"Label":"KLOV-A.ST","Name":"Klvern AB Ser. A","Change":"-2.46%","Volume":71609,"Open":9.85,"DaysLow":9.30,"DaysHigh":9.85,"LastTradePriceOnly":9.30,"LastTradeTime":"2:16pm","LastTradeDate":"11/28/2016"},{"Label":"KLOV-B.ST","Name":"Klvern AB Ser. B","Change":"-2.13%","Volume":1019692,"Open":9.70,"DaysLow":9.42,"DaysHigh":9.70,"LastTradePriceOnly":9.43,"LastTradeTime":"2:16pm","LastTradeDate":"11/28/2016"},{"Label":"KLOV-PREF.ST","Name":"Klvern AB pref","Change":"+0.63%","Volume":11117,"Open":299.00,"DaysLow":298.80,"DaysHigh":302.50,"LastTradePriceOnly":301.90,"LastTradeTime":"2:13pm","LastTradeDate":"11/28/2016"},{"Label":"KLED.ST","Name":"Kungsleden AB","Change":"+0.00%","Volume":163575,"Open":56.25,"DaysLow":55.75,"DaysHigh":56.25,"LastTradePriceOnly":56.00,"LastTradeTime":"2:11pm","LastTradeDate":"11/28/2016"},{"Label":"LAGR-B.ST","Name":"Lagercrantz Group AB ser B","Change":"-0.33%","Volume":17650,"Open":76.25,"DaysLow":74.00,"DaysHigh":76.25,"LastTradePriceOnly":76.00,"LastTradeTime":"2:13pm","LastTradeDate":"11/28/2016"},{"Label":"LIAB.ST","Name":"Lindab International AB","Change":"-0.66%","Volume":29607,"Open":76.10,"DaysLow":75.40,"DaysHigh":76.65,"LastTradePriceOnly":75.70,"LastTradeTime":"2:07pm","LastTradeDate":"11/28/2016"},{"Label":"LUC.ST","Name":"Lucara Diamond Corp","Change":"+0.87%","Volume":204958,"Open":23.00,"DaysLow":22.60,"DaysHigh":23.20,"LastTradePriceOnly":23.10,"LastTradeTime":"2:17pm","LastTradeDate":"11/28/2016"},{"Label":"LUG.ST","Name":"Lundin Gold Inc.","Change":"+1.39%","Volume":30219,"Open":36.50,"DaysLow":36.10,"DaysHigh":37.00,"LastTradePriceOnly":36.50,"LastTradeTime":"2:15pm","LastTradeDate":"11/28/2016"},{"Label":"MVIR-B.ST","Name":"Medivir AB ser. B","Change":"-0.33%","Volume":19042,"Open":76.00,"DaysLow":74.50,"DaysHigh":76.00,"LastTradePriceOnly":75.50,"LastTradeTime":"2:05pm","LastTradeDate":"11/28/2016"},{"Label":"MEKO.ST","Name":"Mekonomen AB","Change":"+8.82%","Volume":212048,"Open":158.00,"DaysLow":156.50,"DaysHigh":168.00,"LastTradePriceOnly":166.50,"LastTradeTime":"2:11pm","LastTradeDate":"11/28/2016"},{"Label":"MUNK1S.ST","Name":"Munksj Oyj","Change":"-1.60%","Volume":5404,"Open":158.00,"DaysLow":151.00,"DaysHigh":158.00,"LastTradePriceOnly":153.50,"LastTradeTime":"2:07pm","LastTradeDate":"11/28/2016"},{"Label":"NDX.ST","Name":"Nordax Group AB","Change":"-0.20%","Volume":45684,"Open":49.60,"DaysLow":49.10,"DaysHigh":49.70,"LastTradePriceOnly":49.60,"LastTradeTime":"2:17pm","LastTradeDate":"11/28/2016"},{"Label":"ORI.ST","Name":"Oriflame Holding AG","Change":"-3.83%","Volume":171813,"Open":232.40,"DaysLow":222.40,"DaysHigh":233.10,"LastTradePriceOnly":223.60,"LastTradeTime":"2:17pm","LastTradeDate":"11/28/2016"},{"Label":"SHOT.ST","Name":"Scandic Hotels Group AB","Change":"-0.32%","Volume":65770,"Open":77.50,"DaysLow":76.50,"DaysHigh":77.50,"LastTradePriceOnly":77.00,"LastTradeTime":"2:09pm","LastTradeDate":"11/28/2016"},{"Label":"THULE.ST","Name":"Thule Group AB","Change":"-1.56%","Volume":108338,"Open":128.00,"DaysLow":125.75,"DaysHigh":128.75,"LastTradePriceOnly":126.50,"LastTradeTime":"2:10pm","LastTradeDate":"11/28/2016"},{"Label":"TOBII.ST","Name":"Tobii AB","Change":"-1.08%","Volume":104117,"Open":70.25,"DaysLow":69.00,"DaysHigh":70.50,"LastTradePriceOnly":69.00,"LastTradeTime":"2:17pm","LastTradeDate":"11/28/2016"},{"Label":"TROAX.ST","Name":"Troax Group AB","Change":"+0.00%","Volume":1651,"Open":155.00,"DaysLow":155.00,"DaysHigh":159.00,"LastTradePriceOnly":157.50,"LastTradeTime":"12:33pm","LastTradeDate":"11/28/2016"},{"Label":"VNV-SDB.ST","Name":"Vostok New Ventures Ltd","Change":"+2.97%","Volume":19733,"Open":66.50,"DaysLow":66.50,"DaysHigh":69.50,"LastTradePriceOnly":69.25,"LastTradeTime":"2:14pm","LastTradeDate":"11/28/2016"},{"Label":"NMAN.ST","Name":"Nederman Holding AB","Change":"-1.04%","Volume":49,"Open":191.00,"DaysLow":190.00,"DaysHigh":191.00,"LastTradePriceOnly":190.00,"LastTradeTime":"12:45pm","LastTradeDate":"11/28/2016"},{"Label":"NET-B.ST","Name":"NetEnt AB ser. B","Change":"-2.25%","Volume":149833,"Open":68.70,"DaysLow":67.20,"DaysHigh":68.95,"LastTradePriceOnly":67.45,"LastTradeTime":"2:16pm","LastTradeDate":"11/28/2016"},{"Label":"NEWA-B.ST","Name":"New Wave Group AB ser. B","Change":"-0.85%","Volume":32138,"Open":46.80,"DaysLow":46.20,"DaysHigh":46.80,"LastTradePriceOnly":46.50,"LastTradeTime":"2:13pm","LastTradeDate":"11/28/2016"},{"Label":"NGQ.ST","Name":"NGEx Resources Inc","Change":"-1.74%","Volume":38255,"Open":8.50,"DaysLow":8.40,"DaysHigh":8.70,"LastTradePriceOnly":8.45,"LastTradeTime":"1:17pm","LastTradeDate":"11/28/2016"},{"Label":"NOLA-B.ST","Name":"Nolato AB ser. B","Change":"-0.19%","Volume":3152,"Open":260.00,"DaysLow":257.50,"DaysHigh":260.00,"LastTradePriceOnly":259.50,"LastTradeTime":"2:12pm","LastTradeDate":"11/28/2016"},{"Label":"NN-B.ST","Name":"Nordnet AB ser. B","Change":"+0.53%","Volume":85720,"Open":37.50,"DaysLow":37.50,"DaysHigh":37.70,"LastTradePriceOnly":37.70,"LastTradeTime":"2:17pm","LastTradeDate":"11/28/2016"},{"Label":"NP3.ST","Name":"NP3 Fastigheter AB","Change":"+0.90%","Volume":20410,"Open":44.00,"DaysLow":44.00,"DaysHigh":45.00,"LastTradePriceOnly":45.00,"LastTradeTime":"2:05pm","LastTradeDate":"11/28/2016"},{"Label":"OASM.ST","Name":"Oasmia Pharmaceutical AB","Change":"+0.96%","Volume":448638,"Open":10.55,"DaysLow":10.30,"DaysHigh":10.70,"LastTradePriceOnly":10.55,"LastTradeTime":"2:10pm","LastTradeDate":"11/28/2016"},{"Label":"OEM-B.ST","Name":"OEM International AB ser. B","Change":"+0.00%","Volume":653,"Open":148.00,"DaysLow":147.50,"DaysHigh":148.00,"LastTradePriceOnly":148.00,"LastTradeTime":"1:52pm","LastTradeDate":"11/28/2016"},{"Label":"OPUS.ST","Name":"Opus Group AB","Change":"+0.77%","Volume":483786,"Open":6.45,"DaysLow":6.40,"DaysHigh":6.60,"LastTradePriceOnly":6.55,"LastTradeTime":"2:12pm","LastTradeDate":"11/28/2016"},{"Label":"ORX.ST","Name":"Orexo AB","Change":"+7.90%","Volume":383431,"Open":37.10,"DaysLow":36.70,"DaysHigh":41.30,"LastTradePriceOnly":39.60,"LastTradeTime":"2:13pm","LastTradeDate":"11/28/2016"},{"Label":"PLAZ-B.ST","Name":"Platzer Fastigheter Holding AB ","Change":"+0.54%","Volume":76718,"Open":47.00,"DaysLow":46.50,"DaysHigh":47.90,"LastTradePriceOnly":46.55,"LastTradeTime":"2:14pm","LastTradeDate":"11/28/2016"},{"Label":"QLRO.ST","Name":"Qliro Group AB","Change":"-3.11%","Volume":85235,"Open":9.60,"DaysLow":9.30,"DaysHigh":9.65,"LastTradePriceOnly":9.35,"LastTradeTime":"2:16pm","LastTradeDate":"11/28/2016"},{"Label":"RECI-B.ST","Name":"Recipharm AB","Change":"-1.38%","Volume":18763,"Open":126.00,"DaysLow":122.75,"DaysHigh":126.00,"LastTradePriceOnly":125.00,"LastTradeTime":"2:13pm","LastTradeDate":"11/28/2016"},{"Label":"REZT.ST","Name":"Rezidor Hotel Group AB","Change":"-0.73%","Volume":59325,"Open":34.90,"DaysLow":33.90,"DaysHigh":34.90,"LastTradePriceOnly":33.95,"LastTradeTime":"2:04pm","LastTradeDate":"11/28/2016"},{"Label":"SAGA-A.ST","Name":"Sagax AB A","Change":"+4.82%","Volume":274,"Open":93.00,"DaysLow":91.50,"DaysHigh":96.00,"LastTradePriceOnly":92.50,"LastTradeTime":"1:52pm","LastTradeDate":"11/28/2016"},{"Label":"SAGA-B.ST","Name":"Sagax AB B","Change":"+0.65%","Volume":48461,"Open":77.50,"DaysLow":77.25,"DaysHigh":78.25,"LastTradePriceOnly":77.75,"LastTradeTime":"2:11pm","LastTradeDate":"11/28/2016"},{"Label":"SAGA-PREF.ST","Name":"Sagax AB pref","Change":"+0.00%","Volume":13717,"Open":32.20,"DaysLow":32.10,"DaysHigh":32.70,"LastTradePriceOnly":32.20,"LastTradeTime":"1:54pm","LastTradeDate":"11/28/2016"},{"Label":"SCST.ST","Name":"Scandi Standard AB","Change":"-1.92%","Volume":312950,"Open":52.00,"DaysLow":49.90,"DaysHigh":52.00,"LastTradePriceOnly":51.00,"LastTradeTime":"2:16pm","LastTradeDate":"11/28/2016"},{"Label":"SPOR.ST","Name":"Sportamore AB","Change":"+0.36%","Volume":10301,"Open":69.50,"DaysLow":69.50,"DaysHigh":71.50,"LastTradePriceOnly":70.50,"LastTradeTime":"2:02pm","LastTradeDate":"11/28/2016"},{"Label":"SAS.ST","Name":"SAS AB","Change":"-1.68%","Volume":294440,"Open":14.85,"DaysLow":14.55,"DaysHigh":14.85,"LastTradePriceOnly":14.65,"LastTradeTime":"1:51pm","LastTradeDate":"11/28/2016"},{"Label":"SAS-PREF.ST","Name":"SAS AB PREF","Change":"-0.56%","Volume":13401,"Open":534.00,"DaysLow":529.00,"DaysHigh":534.00,"LastTradePriceOnly":531.00,"LastTradeTime":"2:12pm","LastTradeDate":"11/28/2016"},{"Label":"SECT-B.ST","Name":"SECTRA AB ser B","Change":"-1.72%","Volume":1888,"Open":129.00,"DaysLow":127.50,"DaysHigh":130.50,"LastTradePriceOnly":128.75,"LastTradeTime":"12:46pm","LastTradeDate":"11/28/2016"},{"Label":"SMF.ST","Name":"Semafo Inc.","Change":"-0.62%","Volume":82513,"Open":27.92,"DaysLow":27.20,"DaysHigh":27.92,"LastTradePriceOnly":27.37,"LastTradeTime":"2:15pm","LastTradeDate":"11/28/2016"},{"Label":"SKIS-B.ST","Name":"SkiStar AB ser. B","Change":"+0.32%","Volume":6855,"Open":155.50,"DaysLow":151.50,"DaysHigh":156.00,"LastTradePriceOnly":156.00,"LastTradeTime":"2:14pm","LastTradeDate":"11/28/2016"},{"Label":"COOR.ST","Name":"Coor Service Management Holding","Change":"+0.48%","Volume":37379,"Open":52.75,"DaysLow":51.25,"DaysHigh":52.75,"LastTradePriceOnly":52.25,"LastTradeTime":"2:00pm","LastTradeDate":"11/28/2016"},{"Label":"DCAR-B.ST","Name":"D. Carnegie & Co AB B","Change":"+0.00%","Volume":44081,"Open":102.75,"DaysLow":101.75,"DaysHigh":102.75,"LastTradePriceOnly":101.75,"LastTradeTime":"2:06pm","LastTradeDate":"11/28/2016"},{"Label":"HOFI.ST","Name":"Hoist Finance AB","Change":"-2.13%","Volume":93639,"Open":82.25,"DaysLow":78.50,"DaysHigh":82.25,"LastTradePriceOnly":80.50,"LastTradeTime":"2:11pm","LastTradeDate":"11/28/2016"},{"Label":"IVSO.ST","Name":"Invisio Communications AB","Change":"+0.37%","Volume":24982,"Open":67.25,"DaysLow":66.50,"DaysHigh":68.00,"LastTradePriceOnly":67.50,"LastTradeTime":"2:16pm","LastTradeDate":"11/28/2016"},{"Label":"MYCR.ST","Name":"Mycronic AB","Change":"-1.30%","Volume":93846,"Open":96.00,"DaysLow":93.75,"DaysHigh":96.00,"LastTradePriceOnly":94.75,"LastTradeTime":"2:12pm","LastTradeDate":"11/28/2016"},{"Label":"NOBINA.ST","Name":"Nobina AB","Change":"-0.44%","Volume":58905,"Open":57.00,"DaysLow":56.00,"DaysHigh":57.00,"LastTradePriceOnly":56.75,"LastTradeTime":"2:16pm","LastTradeDate":"11/28/2016"},{"Label":"SWEC-A.ST","Name":"SWECO AB ser. A","Change":"-3.47%","Volume":428,"Open":245.00,"DaysLow":225.00,"DaysHigh":245.00,"LastTradePriceOnly":236.50,"LastTradeTime":"12:21pm","LastTradeDate":"11/28/2016"},{"Label":"SWEC-B.ST","Name":"SWECO AB ser. B","Change":"-0.16%","Volume":14393,"Open":182.00,"DaysLow":179.90,"DaysHigh":182.00,"LastTradePriceOnly":181.80,"LastTradeTime":"2:16pm","LastTradeDate":"11/28/2016"},{"Label":"SWOL-B.ST","Name":"Swedol AB ser. B","Change":"-0.43%","Volume":10031,"Open":23.00,"DaysLow":22.80,"DaysHigh":23.10,"LastTradePriceOnly":22.90,"LastTradeTime":"2:16pm","LastTradeDate":"11/28/2016"},{"Label":"SYSR.ST","Name":"Systemair AB","Change":"+0.85%","Volume":12310,"Open":119.50,"DaysLow":118.50,"DaysHigh":119.50,"LastTradePriceOnly":119.25,"LastTradeTime":"2:16pm","LastTradeDate":"11/28/2016"},{"Label":"TETY.ST","Name":"Tethys Oil AB","Change":"+1.51%","Volume":35840,"Open":66.00,"DaysLow":65.25,"DaysHigh":67.75,"LastTradePriceOnly":67.25,"LastTradeTime":"2:14pm","LastTradeDate":"11/28/2016"},{"Label":"TWW.ST","Name":"Transcom WorldWide AB","Change":"-1.54%","Volume":5325,"Open":64.00,"DaysLow":63.25,"DaysHigh":64.75,"LastTradePriceOnly":64.00,"LastTradeTime":"1:20pm","LastTradeDate":"11/28/2016"},{"Label":"OP.ST","Name":"Oscar Properties Holding AB","Change":"-1.18%","Volume":25030,"Open":86.00,"DaysLow":82.25,"DaysHigh":86.00,"LastTradePriceOnly":83.50,"LastTradeTime":"2:13pm","LastTradeDate":"11/28/2016"},{"Label":"ALIG.ST","Name":"Alimak Group AB","Change":"+1.32%","Volume":16914,"Open":114.00,"DaysLow":112.00,"DaysHigh":115.00,"LastTradePriceOnly":115.00,"LastTradeTime":"2:16pm","LastTradeDate":"11/28/2016"},{"Label":"ATT.ST","Name":"Attendo AB","Change":"-0.32%","Volume":12934,"Open":79.25,"DaysLow":76.75,"DaysHigh":79.25,"LastTradePriceOnly":78.00,"LastTradeTime":"2:15pm","LastTradeDate":"11/28/2016"},{"Label":"BRAV.ST","Name":"Bravida Holding AB","Change":"-0.48%","Volume":113580,"Open":52.50,"DaysLow":51.75,"DaysHigh":52.75,"LastTradePriceOnly":52.25,"LastTradeTime":"2:15pm","LastTradeDate":"11/28/2016"},{"Label":"CAMX.ST","Name":"Camurus AB","Change":"+0.84%","Volume":9773,"Open":119.50,"DaysLow":119.50,"DaysHigh":121.00,"LastTradePriceOnly":120.50,"LastTradeTime":"2:05pm","LastTradeDate":"11/28/2016"},{"Label":"HTRO.ST","Name":"Hexatronic Group AB","Change":"+0.00%","Volume":36587,"Open":31.70,"DaysLow":30.30,"DaysHigh":31.70,"LastTradePriceOnly":31.50,"LastTradeTime":"2:09pm","LastTradeDate":"11/28/2016"},{"Label":"HMED.ST","Name":"Hansa Medical AB","Change":"+0.43%","Volume":59814,"Open":120.00,"DaysLow":115.75,"DaysHigh":120.00,"LastTradePriceOnly":116.25,"LastTradeTime":"2:14pm","LastTradeDate":"11/28/2016"},{"Label":"OP-PREF.ST","Name":"Oscar Properties Holding AB PRE","Change":"+0.19%","Volume":6432,"Open":261.00,"DaysLow":259.00,"DaysHigh":261.50,"LastTradePriceOnly":260.00,"LastTradeTime":"2:08pm","LastTradeDate":"11/28/2016"},{"Label":"UNIB-SDB.ST","Name":"Unibet Group plc","Change":"-0.63%","Volume":207485,"Open":79.50,"DaysLow":78.65,"DaysHigh":79.50,"LastTradePriceOnly":79.00,"LastTradeTime":"2:17pm","LastTradeDate":"11/28/2016"},{"Label":"VBG-B.ST","Name":"VBG GROUP AB ser. B","Change":"+0.00%","Volume":1681,"Open":157.00,"DaysLow":156.00,"DaysHigh":157.50,"LastTradePriceOnly":156.00,"LastTradeTime":"1:48pm","LastTradeDate":"11/28/2016"},{"Label":"VICP-A.ST","Name":"Victoria Park AB ser. A","Change":"+0.00%","Volume":196881,"Open":23.00,"DaysLow":22.50,"DaysHigh":24.00,"LastTradePriceOnly":23.00,"LastTradeTime":"2:12pm","LastTradeDate":"11/28/2016"},{"Label":"VICP-B.ST","Name":"Victoria Park AB ser. B","Change":"+0.45%","Volume":58422,"Open":22.40,"DaysLow":22.00,"DaysHigh":22.50,"LastTradePriceOnly":22.40,"LastTradeTime":"2:10pm","LastTradeDate":"11/28/2016"},{"Label":"VICP-PREF.ST","Name":"Victoria Park AB Pref","Change":"+0.50%","Volume":1322,"Open":300.00,"DaysLow":300.00,"DaysHigh":301.50,"LastTradePriceOnly":301.50,"LastTradeTime":"2:08pm","LastTradeDate":"11/28/2016"},{"Label":"VITR.ST","Name":"Vitrolife AB","Change":"+2.42%","Volume":31095,"Open":372.50,"DaysLow":365.50,"DaysHigh":381.50,"LastTradePriceOnly":381.50,"LastTradeTime":"2:15pm","LastTradeDate":"11/28/2016"},{"Label":"CLX.ST","Name":"CLX Communications AB","Change":"-0.97%","Volume":2642,"Open":77.50,"DaysLow":75.75,"DaysHigh":78.00,"LastTradePriceOnly":76.25,"LastTradeTime":"11:52am","LastTradeDate":"11/28/2016"},{"Label":"WIHL.ST","Name":"Wihlborgs Fastigheter AB","Change":"-0.30%","Volume":69042,"Open":165.50,"DaysLow":163.90,"DaysHigh":166.10,"LastTradePriceOnly":164.70,"LastTradeTime":"2:16pm","LastTradeDate":"11/28/2016"},{"Label":"AF-B.ST","Name":"F AB ser. B","Change":"+0.00%","Volume":24853,"Open":162.00,"DaysLow":160.00,"DaysHigh":162.00,"LastTradePriceOnly":161.00,"LastTradeTime":"2:16pm","LastTradeDate":"11/28/2016"},{"Label":"ORES.ST","Name":"resund, Investment AB","Change":"-0.66%","Volume":16502,"Open":152.00,"DaysLow":150.50,"DaysHigh":153.50,"LastTradePriceOnly":151.00,"LastTradeTime":"2:13pm","LastTradeDate":"11/28/2016"},{"Label":"COLL.ST","Name":"Collector AB","Change":"+0.52%","Volume":36233,"Open":97.00,"DaysLow":96.75,"DaysHigh":97.75,"LastTradePriceOnly":97.25,"LastTradeTime":"2:15pm","LastTradeDate":"11/28/2016"}]